{"league": "nba", "code": "201611230SAC", "season": "2016-2017", "away": {"players": {"Alex Abrines": {"STL%": 0.0, "": "es", "FT": 0.0, "weight": "190", "3P": 0.0, "TOV": 1.0, "STL/TOV": 0.0, "TSA": 2.0, "2PA": 0.0, "college": "", "FG": 0.0, "3PA": 2.0, "DRB": 0.0, "ORB%": 0.0, "BLK%": 0.0, "AST/TOV": 0.0, "position": "SG", "AST": 0.0, "FT%": null, "3PAr": 1.0, "PF": 0.0, "PTS": 0.0, "FGA": 2.0, "DRBr": null, "ORBr": null, "2P": 0.0, "STL": 0.0, "TRB": 0.0, "TOV%": 33.3, "AST%": 0.0, "FTAr": 0.0, "FTA": 0.0, "FIC": -2.5, "eFG%": 0.0, "BLK": 0.0, "birth_date": "1993-08-01", "FG%": 0.0, "2PAr": 0.0, "FTr": 0.0, "+/-": -5.0, "name": "Alex Abrines", "USG%": 36.8, "DRB%": 0.0, "TS%": 0.0, "experience": 0, "height": 2.0117044623262617, "2P%": null, "MP": 3.85, "DRtg": 130.0, "ORtg": 0.0, "TRB%": 0.0, "FT/FGA": 0.0, "ORB": 0.0, "3P%": 0.0, "HOB": 0.0}, "Anthony Morrow": {"STL%": 0.0, "": "us", "FT": 3.0, "weight": "210", "3P": 1.0, "TOV": 0.0, "STL/TOV": null, "TSA": 9.32, "2PA": 6.0, "college": "Georgia Institute of Technology", "FG": 2.0, "3PA": 2.0, "DRB": 0.0, "ORB%": 0.0, "BLK%": 0.0, "AST/TOV": null, "position": "SG", "AST": 0.0, "FT%": 1.0, "3PAr": 0.25, "PF": 1.0, "PTS": 8.0, "FGA": 8.0, "DRBr": null, "ORBr": null, "2P": 1.0, "STL": 0.0, "TRB": 0.0, "TOV%": 0.0, "AST%": 0.0, "FTAr": 0.375, "FTA": 3.0, "FIC": 0.375, "eFG%": 0.3125, "BLK": 0.0, "birth_date": "1985-09-27", "FG%": 0.25, "2PAr": 0.75, "FTr": 0.375, "+/-": -12.0, "name": "Anthony Morrow", "USG%": 23.2, "DRB%": 0.0, "TS%": 0.4291845493562232, "experience": 8, "height": 1.9812240916849548, "2P%": 0.16666666666666666, "MP": 18.916666666666668, "DRtg": 130.0, "ORtg": 89.0, "TRB%": 0.0, "FT/FGA": 0.375, "ORB": 0.0, "3P%": 0.5, "HOB": 0.0625}, "Enes Kanter": {"STL%": 2.4, "": "ch", "FT": 4.0, "weight": "245", "3P": 0.0, "TOV": 0.0, "STL/TOV": null, "TSA": 10.76, "2PA": 8.0, "college": "", "FG": 3.0, "3PA": 1.0, "DRB": 5.0, "ORB%": 11.4, "BLK%": 0.0, "AST/TOV": null, "position": "C", "AST": 1.0, "FT%": 1.0, "3PAr": 0.1111111111111111, "PF": 2.0, "PTS": 10.0, "FGA": 9.0, "DRBr": 0.7142857142857143, "ORBr": 0.2857142857142857, "2P": 3.0, "STL": 1.0, "TRB": 7.0, "TOV%": 0.0, "AST%": 9.1, "FTAr": 0.4444444444444444, "FTA": 4.0, "FIC": 8.5, "eFG%": 0.3333333333333333, "BLK": 0.0, "birth_date": "1992-05-20", "FG%": 0.3333333333333333, "2PAr": 0.8888888888888888, "FTr": 0.444, "+/-": 3.0, "name": "Enes Kanter", "USG%": 24.1, "DRB%": 25.9, "TS%": 0.4646840148698885, "experience": 5, "height": 1.8623506461838577, "2P%": 0.375, "MP": 21.033333333333335, "DRtg": 117.0, "ORtg": 109.0, "TRB%": 19.0, "FT/FGA": 0.4444444444444444, "ORB": 2.0, "3P%": 0.0, "HOB": 0.125}, "Joffrey Lauvergne": {"STL%": 0.0, "": "fr", "FT": 0.0, "weight": "220", "3P": 1.0, "TOV": 2.0, "STL/TOV": 0.0, "TSA": 2.0, "2PA": 1.0, "college": "", "FG": 1.0, "3PA": 1.0, "DRB": 0.0, "ORB%": 21.7, "BLK%": 0.0, "AST/TOV": 0.0, "position": "PF", "AST": 0.0, "FT%": null, "3PAr": 0.5, "PF": 0.0, "PTS": 3.0, "FGA": 2.0, "DRBr": 0.0, "ORBr": 1.0, "2P": 0.0, "STL": 0.0, "TRB": 1.0, "TOV%": 50.0, "AST%": 0.0, "FTAr": 0.0, "FTA": 0.0, "FIC": 0.5, "eFG%": 0.75, "BLK": 0.0, "birth_date": "1991-09-30", "FG%": 0.5, "2PAr": 0.5, "FTr": 0.0, "+/-": -7.0, "name": "Joffrey Lauvergne", "USG%": 34.1, "DRB%": 0.0, "TS%": 0.75, "experience": 2, "height": 1.8623506461838577, "2P%": 0.0, "MP": 5.533333333333333, "DRtg": 130.0, "ORtg": 74.0, "TRB%": 10.3, "FT/FGA": 0.0, "ORB": 1.0, "3P%": 1.0, "HOB": 0.03125}, "Russell Westbrook": {"STL%": 2.8, "": "us", "FT": 16.0, "weight": "200", "3P": 1.0, "TOV": 3.0, "STL/TOV": 0.6666666666666666, "TSA": 26.36, "2PA": 13.0, "college": "University of California, Los Angeles", "FG": 7.0, "3PA": 5.0, "DRB": 10.0, "ORB%": 3.4, "BLK%": 0.0, "AST/TOV": 3.0, "position": "PG", "AST": 9.0, "FT%": 0.8421052631578947, "3PAr": 0.2777777777777778, "PF": 1.0, "PTS": 31.0, "FGA": 18.0, "DRBr": 0.9090909090909091, "ORBr": 0.09090909090909091, "2P": 6.0, "STL": 2.0, "TRB": 11.0, "TOV%": 10.2, "AST%": 55.0, "FTAr": 1.0555555555555556, "FTA": 19.0, "FIC": 26.375, "eFG%": 0.4166666666666667, "BLK": 0.0, "birth_date": "1988-11-12", "FG%": 0.3888888888888889, "2PAr": 0.7222222222222222, "FTr": 1.056, "+/-": -7.0, "name": "Russell Westbrook", "USG%": 39.5, "DRB%": 31.1, "TS%": 0.5880121396054628, "experience": 8, "height": 1.9202633504023408, "2P%": 0.46153846153846156, "MP": 35.06666666666667, "DRtg": 114.0, "ORtg": 120.0, "TRB%": 17.9, "FT/FGA": 0.8888888888888888, "ORB": 1.0, "3P%": 0.2, "HOB": 0.5}, "Andre Roberson": {"STL%": 1.4, "": "us", "FT": 1.0, "weight": "210", "3P": 1.0, "TOV": 0.0, "STL/TOV": null, "TSA": 7.88, "2PA": 3.0, "college": "University of Colorado", "FG": 4.0, "3PA": 4.0, "DRB": 4.0, "ORB%": 3.4, "BLK%": 4.1, "AST/TOV": null, "position": "SF", "AST": 1.0, "FT%": 0.5, "3PAr": 0.5714285714285714, "PF": 4.0, "PTS": 10.0, "FGA": 7.0, "DRBr": 0.8, "ORBr": 0.2, "2P": 3.0, "STL": 1.0, "TRB": 5.0, "TOV%": 0.0, "AST%": 5.1, "FTAr": 0.2857142857142857, "FTA": 2.0, "FIC": 10.0, "eFG%": 0.6428571428571429, "BLK": 2.0, "birth_date": "1991-12-04", "FG%": 0.5714285714285714, "2PAr": 0.42857142857142855, "FTr": 0.286, "+/-": -2.0, "name": "Andre Roberson", "USG%": 10.6, "DRB%": 12.4, "TS%": 0.6345177664974619, "experience": 3, "height": 2.042184832967569, "2P%": 1.0, "MP": 35.166666666666664, "DRtg": 119.0, "ORtg": 131.0, "TRB%": 8.1, "FT/FGA": 0.14285714285714285, "ORB": 1.0, "3P%": 0.25, "HOB": 0.15625}, "Jerami Grant": {"STL%": 1.6, "": "us", "FT": 2.0, "weight": "210", "3P": 0.0, "TOV": 0.0, "STL/TOV": null, "TSA": 6.76, "2PA": 3.0, "college": "Syracuse University", "FG": 2.0, "3PA": 2.0, "DRB": 3.0, "ORB%": 0.0, "BLK%": 2.3, "AST/TOV": null, "position": "SF", "AST": 1.0, "FT%": 0.5, "3PAr": 0.4, "PF": 2.0, "PTS": 6.0, "FGA": 5.0, "DRBr": 1.0, "ORBr": 0.0, "2P": 2.0, "STL": 1.0, "TRB": 3.0, "TOV%": 0.0, "AST%": 5.2, "FTAr": 0.8, "FTA": 4.0, "FIC": 5.0, "eFG%": 0.4, "BLK": 1.0, "birth_date": "1994-03-12", "FG%": 0.4, "2PAr": 0.6, "FTr": 0.8, "+/-": -4.0, "name": "Jerami Grant", "USG%": 10.0, "DRB%": 10.3, "TS%": 0.4437869822485207, "experience": 2, "height": 2.0726652036088757, "2P%": 0.6666666666666666, "MP": 31.75, "DRtg": 121.0, "ORtg": 96.0, "TRB%": 5.4, "FT/FGA": 0.4, "ORB": 0.0, "3P%": 0.0, "HOB": 0.09375}, "Domantas Sabonis": {"STL%": 3.4, "": "us", "FT": 0.0, "weight": "240", "3P": 0.0, "TOV": 1.0, "STL/TOV": 1.0, "TSA": 3.0, "2PA": 3.0, "college": "Gonzaga University", "FG": 2.0, "3PA": 0.0, "DRB": 0.0, "ORB%": 0.0, "BLK%": 0.0, "AST/TOV": 3.0, "position": "PF", "AST": 3.0, "FT%": null, "3PAr": 0.0, "PF": 2.0, "PTS": 4.0, "FGA": 3.0, "DRBr": null, "ORBr": null, "2P": 2.0, "STL": 1.0, "TRB": 0.0, "TOV%": 25.0, "AST%": 39.0, "FTAr": 0.0, "FTA": 0.0, "FIC": 3.75, "eFG%": 0.6666666666666666, "BLK": 0.0, "birth_date": "1996-05-03", "FG%": 0.6666666666666666, "2PAr": 1.0, "FTr": 0.0, "+/-": -9.0, "name": "Domantas Sabonis", "USG%": 13.0, "DRB%": 0.0, "TS%": 0.6666666666666666, "experience": 0, "height": 1.8623506461838577, "2P%": 0.6666666666666666, "MP": 14.55, "DRtg": 122.0, "ORtg": 115.0, "TRB%": 0.0, "FT/FGA": 0.0, "ORB": 0.0, "3P%": null, "HOB": 0.15625}, "Semaj Christon": {"STL%": 0.0, "": "us", "FT": 0.0, "weight": "190", "3P": 0.0, "TOV": 0.0, "STL/TOV": null, "TSA": 0.0, "2PA": 0.0, "college": "Xavier University", "FG": 0.0, "3PA": 0.0, "DRB": 0.0, "ORB%": 0.0, "BLK%": 0.0, "AST/TOV": null, "position": "PG", "AST": 1.0, "FT%": null, "3PAr": null, "PF": 3.0, "PTS": 0.0, "FGA": 0.0, "DRBr": null, "ORBr": null, "2P": 0.0, "STL": 0.0, "TRB": 0.0, "TOV%": null, "AST%": 18.5, "FTAr": null, "FTA": 0.0, "FIC": -0.5, "eFG%": null, "BLK": 0.0, "birth_date": "1992-11-01", "FG%": null, "2PAr": null, "FTr": null, "+/-": -3.0, "name": "Semaj Christon", "USG%": 0.0, "DRB%": 0.0, "TS%": null, "experience": 0, "height": 1.9202633504023408, "2P%": null, "MP": 8.1, "DRtg": 129.0, "ORtg": 222.0, "TRB%": 0.0, "FT/FGA": null, "ORB": 0.0, "3P%": null, "HOB": 0.03125}, "Nick Collison": {"": "us", "name": "Nick Collison", "weight": "255", "experience": 12, "height": 1.8593026091197267, "college": "University of Kansas", "MP": 0.0, "birth_date": "1980-10-26", "position": "PF"}, "Steven Adams": {"STL%": 0.0, "": "nz", "FT": 3.0, "weight": "255", "3P": 0.0, "TOV": 0.0, "STL/TOV": null, "TSA": 8.76, "2PA": 7.0, "college": "University of Pittsburgh", "FG": 4.0, "3PA": 0.0, "DRB": 4.0, "ORB%": 0.0, "BLK%": 5.1, "AST/TOV": null, "position": "C", "AST": 0.0, "FT%": 0.75, "3PAr": 0.0, "PF": 3.0, "PTS": 11.0, "FGA": 7.0, "DRBr": 1.0, "ORBr": 0.0, "2P": 4.0, "STL": 0.0, "TRB": 4.0, "TOV%": 0.0, "AST%": 0.0, "FTAr": 0.5714285714285714, "FTA": 4.0, "FIC": 7.75, "eFG%": 0.5714285714285714, "BLK": 2.0, "birth_date": "1993-07-20", "FG%": 0.5714285714285714, "2PAr": 1.0, "FTr": 0.571, "+/-": -19.0, "name": "Steven Adams", "USG%": 14.6, "DRB%": 15.4, "TS%": 0.6278538812785388, "experience": 3, "height": 2.13362594489149, "2P%": 0.5714285714285714, "MP": 28.383333333333333, "DRtg": 121.0, "ORtg": 125.0, "TRB%": 8.1, "FT/FGA": 0.42857142857142855, "ORB": 0.0, "3P%": null, "HOB": 0.125}, "Kyle Singler": {"STL%": 0.0, "": "us", "FT": 0.0, "weight": "228", "3P": 0.0, "TOV": 0.0, "STL/TOV": null, "TSA": 0.0, "2PA": 0.0, "college": "Duke University", "FG": 0.0, "3PA": 0.0, "DRB": 1.0, "ORB%": 0.0, "BLK%": 0.0, "AST/TOV": null, "position": "SF", "AST": 0.0, "FT%": null, "3PAr": null, "PF": 0.0, "PTS": 0.0, "FGA": 0.0, "DRBr": 1.0, "ORBr": 0.0, "2P": 0.0, "STL": 0.0, "TRB": 1.0, "TOV%": null, "AST%": 0.0, "FTAr": null, "FTA": 0.0, "FIC": 0.75, "eFG%": null, "BLK": 0.0, "birth_date": "1988-05-04", "FG%": null, "2PAr": null, "FTr": null, "+/-": 1.0, "name": "Kyle Singler", "USG%": 0.0, "DRB%": 78.9, "TS%": null, "experience": 4, "height": 2.0726652036088757, "2P%": null, "MP": 1.3833333333333333, "DRtg": 107.0, "ORtg": null, "TRB%": 41.3, "FT/FGA": null, "ORB": 0.0, "3P%": null, "HOB": 0.0}, "Victor Oladipo": {"STL%": 1.4, "": "us", "FT": 1.0, "weight": "210", "3P": 3.0, "TOV": 2.0, "STL/TOV": 0.5, "TSA": 15.88, "2PA": 7.0, "college": "Indiana University", "FG": 7.0, "3PA": 8.0, "DRB": 6.0, "ORB%": 0.0, "BLK%": 4.0, "AST/TOV": 1.0, "position": "SG", "AST": 2.0, "FT%": 0.5, "3PAr": 0.5333333333333333, "PF": 3.0, "PTS": 18.0, "FGA": 15.0, "DRBr": 1.0, "ORBr": 0.0, "2P": 4.0, "STL": 1.0, "TRB": 6.0, "TOV%": 11.2, "AST%": 11.6, "FTAr": 0.13333333333333333, "FTA": 2.0, "FIC": 12.0, "eFG%": 0.5666666666666667, "BLK": 2.0, "birth_date": "1992-05-04", "FG%": 0.4666666666666667, "2PAr": 0.4666666666666667, "FTr": 0.133, "+/-": -11.0, "name": "Victor Oladipo", "USG%": 23.3, "DRB%": 18.0, "TS%": 0.5667506297229219, "experience": 3, "height": 1.9507437210436478, "2P%": 0.5714285714285714, "MP": 36.266666666666666, "DRtg": 118.0, "ORtg": 98.0, "TRB%": 9.5, "FT/FGA": 0.06666666666666667, "ORB": 0.0, "3P%": 0.375, "HOB": 0.28125}}, "scores": {"1": "27", "3": "27", "2": "21", "4": "26", "T": "101"}, "name": "Oklahoma City Thunder", "totals": {"STL%": 7.3, "FT": 30.0, "2PA": 51.0, "FG": 32.0, "DRB": 33.0, "ORB%": 12.5, "AST": 18.0, "3PAr": 0.32894736842105265, "PF": 21.0, "FGA": 76.0, "DRBr": 0.868421052631579, "2P": 25.0, "ORBr": 0.13157894736842105, "TOV%": 8.8, "AST%": 56.3, "FTAr": 0.5, "FIC": 72.0, "eFG%": 0.46710526315789475, "FG%": 0.42105263157894735, "2PAr": 0.6710526315789473, "+/-": -15.0, "USG%": 100.0, "DRtg": 120.4, "2P%": 0.49019607843137253, "DRB%": 75.0, "ORtg": 104.8, "TRB%": 45.2, "ORB": 5.0, "3P": 7.0, "TOV": 9.0, "STL/TOV": 0.7777777777777778, "TSA": 92.72, "AST/TOV": 2.0, "3PA": 25.0, "BLK%": 10.6, "FT%": 0.7894736842105263, "PTS": 101.0, "HOB": 1.5625, "STL": 7.0, "TRB": 38.0, "FTA": 38.0, "BLK": 7.0, "FTr": 0.5, "TS%": 0.5446505608283002, "FT/FGA": 0.39473684210526316, "3P%": 0.28}}, "time": "22:30:00", "country": "United States", "date": "2016-11-23", "home": {"players": {"Willie Cauley-Stein": {"": "us", "name": "Willie Cauley-Stein", "weight": "240", "experience": 1, "height": 2.13362594489149, "college": "University of Kentucky", "MP": 0.0, "birth_date": "1993-08-18", "position": "C"}, "Skal Labissiere": {"": "ht", "name": "Skal Labissiere", "weight": "225", "experience": 0, "height": 1.8623506461838577, "college": "University of Kentucky", "MP": 0.0, "birth_date": "1996-03-18", "position": "PF"}, "Garrett Temple": {"STL%": 3.7, "": "us", "FT": 0.0, "weight": "195", "3P": 2.0, "TOV": 0.0, "STL/TOV": null, "TSA": 8.0, "2PA": 3.0, "college": "Louisiana State University", "FG": 3.0, "3PA": 5.0, "DRB": 2.0, "ORB%": 4.1, "BLK%": 0.0, "AST/TOV": null, "position": "SG", "AST": 1.0, "FT%": null, "3PAr": 0.625, "PF": 4.0, "PTS": 8.0, "FGA": 8.0, "DRBr": 0.6666666666666666, "ORBr": 0.3333333333333333, "2P": 1.0, "STL": 2.0, "TRB": 3.0, "TOV%": 0.0, "AST%": 4.7, "FTAr": 0.0, "FTA": 0.0, "FIC": 5.5, "eFG%": 0.5, "BLK": 0.0, "birth_date": "1986-05-08", "FG%": 0.375, "2PAr": 0.375, "FTr": 0.0, "+/-": 15.0, "name": "Garrett Temple", "USG%": 12.8, "DRB%": 9.0, "TS%": 0.5, "experience": 6, "height": 2.0117044623262617, "2P%": 0.3333333333333333, "MP": 26.65, "DRtg": 100.0, "ORtg": 115.0, "TRB%": 6.4, "FT/FGA": 0.0, "ORB": 1.0, "3P%": 0.4, "HOB": 0.09090909090909091}, "Omri Casspi": {"": "il", "name": "Omri Casspi", "weight": "225", "experience": 7, "height": 2.103145574250183, "college": "", "MP": 0.0, "birth_date": "1988-06-22", "position": "SF"}, "Arron Afflalo": {"STL%": 0.0, "": "us", "FT": 2.0, "weight": "210", "3P": 0.0, "TOV": 0.0, "STL/TOV": null, "TSA": 7.88, "2PA": 6.0, "college": "University of California, Los Angeles", "FG": 3.0, "3PA": 1.0, "DRB": 1.0, "ORB%": 0.0, "BLK%": 0.0, "AST/TOV": null, "position": "SG", "AST": 4.0, "FT%": 1.0, "3PAr": 0.14285714285714285, "PF": 1.0, "PTS": 8.0, "FGA": 7.0, "DRBr": 1.0, "ORBr": 0.0, "2P": 3.0, "STL": 0.0, "TRB": 1.0, "TOV%": 0.0, "AST%": 16.1, "FTAr": 0.2857142857142857, "FTA": 2.0, "FIC": 6.25, "eFG%": 0.42857142857142855, "BLK": 0.0, "birth_date": "1985-10-15", "FG%": 0.42857142857142855, "2PAr": 0.8571428571428571, "FTr": 0.286, "+/-": 2.0, "name": "Arron Afflalo", "USG%": 11.1, "DRB%": 4.0, "TS%": 0.5076142131979695, "experience": 9, "height": 1.9812240916849548, "2P%": 0.5, "MP": 30.35, "DRtg": 110.0, "ORtg": 127.0, "TRB%": 1.9, "FT/FGA": 0.2857142857142857, "ORB": 0.0, "3P%": 0.0, "HOB": 0.1590909090909091}, "Kosta Koufos": {"STL%": 3.0, "": "us", "FT": 1.0, "weight": "265", "3P": 0.0, "TOV": 0.0, "STL/TOV": null, "TSA": 7.44, "2PA": 7.0, "college": "Ohio State University", "FG": 4.0, "3PA": 0.0, "DRB": 6.0, "ORB%": 26.3, "BLK%": 0.0, "AST/TOV": null, "position": "C", "AST": 0.0, "FT%": 1.0, "3PAr": 0.0, "PF": 4.0, "PTS": 9.0, "FGA": 7.0, "DRBr": 0.6, "ORBr": 0.4, "2P": 4.0, "STL": 1.0, "TRB": 10.0, "TOV%": 0.0, "AST%": 0.0, "FTAr": 0.14285714285714285, "FTA": 1.0, "FIC": 10.875, "eFG%": 0.5714285714285714, "BLK": 0.0, "birth_date": "1989-02-24", "FG%": 0.5714285714285714, "2PAr": 1.0, "FTr": 0.143, "+/-": 7.0, "name": "Kosta Koufos", "USG%": 19.1, "DRB%": 43.4, "TS%": 0.6048387096774194, "experience": 8, "height": 2.13362594489149, "2P%": 0.5714285714285714, "MP": 16.583333333333332, "DRtg": 97.0, "ORtg": 143.0, "TRB%": 34.5, "FT/FGA": 0.14285714285714285, "ORB": 4.0, "3P%": null, "HOB": 0.09090909090909091}, "Darren Collison": {"STL%": 0.0, "": "us", "FT": 4.0, "weight": "175", "3P": 3.0, "TOV": 4.0, "STL/TOV": 0.0, "TSA": 13.76, "2PA": 7.0, "college": "University of California, Los Angeles", "FG": 7.0, "3PA": 5.0, "DRB": 0.0, "ORB%": 0.0, "BLK%": 0.0, "AST/TOV": 1.5, "position": "PG", "AST": 6.0, "FT%": 1.0, "3PAr": 0.4166666666666667, "PF": 0.0, "PTS": 21.0, "FGA": 12.0, "DRBr": null, "ORBr": null, "2P": 4.0, "STL": 0.0, "TRB": 0.0, "TOV%": 22.5, "AST%": 27.6, "FTAr": 0.3333333333333333, "FTA": 4.0, "FIC": 12.5, "eFG%": 0.7083333333333334, "BLK": 0.0, "birth_date": "1987-08-23", "FG%": 0.5833333333333334, "2PAr": 0.5833333333333334, "FTr": 0.333, "+/-": 4.0, "name": "Darren Collison", "USG%": 24.2, "DRB%": 0.0, "TS%": 0.7630813953488372, "experience": 7, "height": 1.8288222384784198, "2P%": 0.5714285714285714, "MP": 31.366666666666667, "DRtg": 111.0, "ORtg": 125.0, "TRB%": 0.0, "FT/FGA": 0.3333333333333333, "ORB": 0.0, "3P%": 0.6, "HOB": 0.29545454545454547}, "Ben McLemore": {"STL%": 0.0, "": "us", "FT": 0.0, "weight": "195", "3P": 1.0, "TOV": 0.0, "STL/TOV": null, "TSA": 10.0, "2PA": 7.0, "college": "University of Kansas", "FG": 4.0, "3PA": 3.0, "DRB": 2.0, "ORB%": 0.0, "BLK%": 0.0, "AST/TOV": null, "position": "SG", "AST": 0.0, "FT%": null, "3PAr": 0.3, "PF": 3.0, "PTS": 9.0, "FGA": 10.0, "DRBr": 1.0, "ORBr": 0.0, "2P": 3.0, "STL": 0.0, "TRB": 2.0, "TOV%": 0.0, "AST%": 0.0, "FTAr": 0.0, "FTA": 0.0, "FIC": 1.5, "eFG%": 0.45, "BLK": 0.0, "birth_date": "1993-02-11", "FG%": 0.4, "2PAr": 0.7, "FTr": 0.0, "+/-": 14.0, "name": "Ben McLemore", "USG%": 25.3, "DRB%": 14.2, "TS%": 0.45, "experience": 3, "height": 1.9812240916849548, "2P%": 0.42857142857142855, "MP": 16.9, "DRtg": 108.0, "ORtg": 93.0, "TRB%": 6.8, "FT/FGA": 0.0, "ORB": 0.0, "3P%": 0.3333333333333333, "HOB": 0.09090909090909091}, "DeMarcus Cousins": {"STL%": 0.0, "": "us", "FT": 5.0, "weight": "270", "3P": 3.0, "TOV": 2.0, "STL/TOV": 0.0, "TSA": 30.64, "2PA": 23.0, "college": "University of Kentucky", "FG": 14.0, "3PA": 5.0, "DRB": 11.0, "ORB%": 6.3, "BLK%": 0.0, "AST/TOV": 1.0, "position": "C", "AST": 2.0, "FT%": 0.8333333333333334, "3PAr": 0.17857142857142858, "PF": 3.0, "PTS": 36.0, "FGA": 28.0, "DRBr": 0.8461538461538461, "ORBr": 0.15384615384615385, "2P": 11.0, "STL": 0.0, "TRB": 13.0, "TOV%": 6.1, "AST%": 11.3, "FTAr": 0.21428571428571427, "FTA": 6.0, "FIC": 21.5, "eFG%": 0.5535714285714286, "BLK": 0.0, "birth_date": "1990-08-13", "FG%": 0.5, "2PAr": 0.8214285714285714, "FTr": 0.214, "+/-": 7.0, "name": "DeMarcus Cousins", "USG%": 40.3, "DRB%": 38.2, "TS%": 0.5874673629242819, "experience": 6, "height": 1.8623506461838577, "2P%": 0.4782608695652174, "MP": 34.56666666666667, "DRtg": 105.0, "ORtg": 117.0, "TRB%": 21.5, "FT/FGA": 0.17857142857142858, "ORB": 2.0, "3P%": 0.6, "HOB": 0.36363636363636365}, "Anthony Tolliver": {"": "us", "name": "Anthony Tolliver", "weight": "240", "experience": 8, "height": 2.0726652036088757, "college": "Creighton University", "MP": 0.0, "birth_date": "1985-06-01", "position": "PF"}, "Ty Lawson": {"STL%": 2.4, "": "us", "FT": 2.0, "weight": "195", "3P": 0.0, "TOV": 2.0, "STL/TOV": 0.5, "TSA": 4.88, "2PA": 4.0, "college": "University of North Carolina", "FG": 3.0, "3PA": 0.0, "DRB": 3.0, "ORB%": 5.3, "BLK%": 0.0, "AST/TOV": 2.0, "position": "PG", "AST": 4.0, "FT%": 1.0, "3PAr": 0.0, "PF": 3.0, "PTS": 8.0, "FGA": 4.0, "DRBr": 0.75, "ORBr": 0.25, "2P": 3.0, "STL": 1.0, "TRB": 4.0, "TOV%": 29.1, "AST%": 25.3, "FTAr": 0.5, "FTA": 2.0, "FIC": 9.0, "eFG%": 0.75, "BLK": 0.0, "birth_date": "1987-11-03", "FG%": 0.75, "2PAr": 1.0, "FTr": 0.5, "+/-": 12.0, "name": "Ty Lawson", "USG%": 14.3, "DRB%": 17.5, "TS%": 0.819672131147541, "experience": 7, "height": 1.5575469397707877, "2P%": 0.75, "MP": 20.533333333333335, "DRtg": 102.0, "ORtg": 133.0, "TRB%": 11.1, "FT/FGA": 0.5, "ORB": 1.0, "3P%": null, "HOB": 0.1590909090909091}, "Matt Barnes": {"STL%": 0.0, "": "us", "FT": 0.0, "weight": "226", "3P": 0.0, "TOV": 1.0, "STL/TOV": 0.0, "TSA": 3.0, "2PA": 0.0, "college": "University of California, Los Angeles", "FG": 0.0, "3PA": 3.0, "DRB": 3.0, "ORB%": 3.7, "BLK%": 3.2, "AST/TOV": 5.0, "position": "SF", "AST": 5.0, "FT%": null, "3PAr": 1.0, "PF": 2.0, "PTS": 0.0, "FGA": 3.0, "DRBr": 0.75, "ORBr": 0.25, "2P": 0.0, "STL": 0.0, "TRB": 4.0, "TOV%": 25.0, "AST%": 18.5, "FTAr": 0.0, "FTA": 0.0, "FIC": 5.0, "eFG%": 0.0, "BLK": 1.0, "birth_date": "1980-03-09", "FG%": 0.0, "2PAr": 0.0, "FTr": 0.0, "+/-": 17.0, "name": "Matt Barnes", "USG%": 5.8, "DRB%": 12.2, "TS%": 0.0, "experience": 13, "height": 2.042184832967569, "2P%": null, "MP": 29.45, "DRtg": 106.0, "ORtg": 76.0, "TRB%": 7.8, "FT/FGA": 0.0, "ORB": 1.0, "3P%": 0.0, "HOB": 0.11363636363636363}, "Rudy Gay": {"STL%": 0.0, "": "us", "FT": 2.0, "weight": "230", "3P": 3.0, "TOV": 2.0, "STL/TOV": 0.0, "TSA": 15.88, "2PA": 9.0, "college": "University of Connecticut", "FG": 6.0, "3PA": 6.0, "DRB": 7.0, "ORB%": 6.5, "BLK%": 0.0, "AST/TOV": 2.0, "position": "SF", "AST": 4.0, "FT%": 1.0, "3PAr": 0.4, "PF": 3.0, "PTS": 17.0, "FGA": 15.0, "DRBr": 0.7777777777777778, "ORBr": 0.2222222222222222, "2P": 3.0, "STL": 0.0, "TRB": 9.0, "TOV%": 11.2, "AST%": 16.1, "FTAr": 0.13333333333333333, "FTA": 2.0, "FIC": 12.75, "eFG%": 0.5, "BLK": 0.0, "birth_date": "1986-08-17", "FG%": 0.4, "2PAr": 0.6, "FTr": 0.133, "+/-": -3.0, "name": "Rudy Gay", "USG%": 22.7, "DRB%": 25.0, "TS%": 0.535264483627204, "experience": 10, "height": 2.0726652036088757, "2P%": 0.3333333333333333, "MP": 33.6, "DRtg": 107.0, "ORtg": 111.0, "TRB%": 15.3, "FT/FGA": 0.13333333333333333, "ORB": 2.0, "3P%": 0.5, "HOB": 0.22727272727272727}}, "scores": {"1": "27", "3": "36", "2": "24", "4": "29", "T": "116"}, "name": "Sacramento Kings", "totals": {"STL%": 4.2, "FT": 16.0, "2PA": 66.0, "FG": 44.0, "DRB": 35.0, "ORB%": 25.0, "AST": 26.0, "3PAr": 0.2978723404255319, "PF": 23.0, "FGA": 94.0, "DRBr": 0.7608695652173914, "2P": 32.0, "ORBr": 0.2391304347826087, "TOV%": 9.8, "AST%": 59.1, "FTAr": 0.18085106382978725, "FIC": 84.875, "eFG%": 0.5319148936170213, "FG%": 0.46808510638297873, "2PAr": 0.7021276595744681, "+/-": 15.0, "USG%": 100.0, "DRtg": 104.8, "2P%": 0.48484848484848486, "DRB%": 87.5, "ORtg": 120.4, "TRB%": 54.8, "ORB": 11.0, "3P": 12.0, "TOV": 11.0, "STL/TOV": 0.36363636363636365, "TSA": 101.48, "AST/TOV": 2.3636363636363638, "3PA": 28.0, "BLK%": 2.0, "FT%": 0.9411764705882353, "PTS": 116.0, "HOB": 1.5909090909090908, "STL": 4.0, "TRB": 46.0, "FTA": 17.0, "BLK": 1.0, "FTr": 0.181, "TS%": 0.5715411903823413, "FT/FGA": 0.1702127659574468, "3P%": 0.42857142857142855}}, "type": "Season"}