{"league": "nba", "code": "201612020DEN", "season": "2016-2017", "away": {"players": {"Montrezl Harrell": {"STL%": 0.0, "": "us", "FT": 0.0, "weight": "240", "3P": 0.0, "TOV": 1.0, "STL/TOV": 0.0, "TSA": 6.0, "2PA": 6.0, "college": "University of Louisville", "FG": 4.0, "3PA": 0.0, "DRB": 3.0, "ORB%": 0.0, "BLK%": 6.4, "AST/TOV": 0.0, "position": "C", "AST": 0.0, "FT%": null, "3PAr": 0.0, "PF": 1.0, "PTS": 8.0, "FGA": 6.0, "DRBr": 1.0, "ORBr": 0.0, "2P": 4.0, "STL": 0.0, "TRB": 3.0, "TOV%": 14.3, "AST%": 0.0, "FTAr": 0.0, "FTA": 0.0, "FIC": 6.25, "eFG%": 0.6666666666666666, "BLK": 2.0, "birth_date": "1994-01-26", "FG%": 0.6666666666666666, "2PAr": 1.0, "FTr": 0.0, "+/-": 10.0, "name": "Montrezl Harrell", "USG%": 15.0, "DRB%": 12.8, "TS%": 0.6666666666666666, "experience": 1, "height": 2.0726652036088757, "2P%": 0.6666666666666666, "MP": 20.4, "DRtg": 114.0, "ORtg": 108.0, "TRB%": 7.4, "FT/FGA": 0.0, "ORB": 0.0, "3P%": null, "HOB": 0.08888888888888889}, "Nene Hilario": {"": "br", "name": "Nene Hilario", "weight": "250", "experience": 14, "height": 1.8623506461838577, "college": "", "MP": 0.0, "birth_date": "1982-09-13", "position": "C"}, "Trevor Ariza": {"STL%": 7.8, "": "us", "FT": 0.0, "weight": "215", "3P": 4.0, "TOV": 0.0, "STL/TOV": null, "TSA": 12.0, "2PA": 4.0, "college": "University of California, Los Angeles", "FG": 6.0, "3PA": 8.0, "DRB": 5.0, "ORB%": 7.6, "BLK%": 0.0, "AST/TOV": null, "position": "SF", "AST": 3.0, "FT%": null, "3PAr": 0.6666666666666666, "PF": 1.0, "PTS": 16.0, "FGA": 12.0, "DRBr": 0.7142857142857143, "ORBr": 0.2857142857142857, "2P": 2.0, "STL": 5.0, "TRB": 7.0, "TOV%": 0.0, "AST%": 12.8, "FTAr": 0.0, "FTA": 0.0, "FIC": 20.25, "eFG%": 0.6666666666666666, "BLK": 0.0, "birth_date": "1985-06-30", "FG%": 0.5, "2PAr": 0.3333333333333333, "FTr": 0.0, "+/-": 12.0, "name": "Trevor Ariza", "USG%": 16.7, "DRB%": 13.9, "TS%": 0.6666666666666666, "experience": 12, "height": 2.0726652036088757, "2P%": 0.5, "MP": 31.433333333333334, "DRtg": 99.0, "ORtg": 150.0, "TRB%": 11.3, "FT/FGA": 0.0, "ORB": 2.0, "3P%": 0.5, "HOB": 0.2}, "Eric Gordon": {"STL%": 2.1, "": "us", "FT": 2.0, "weight": "215", "3P": 4.0, "TOV": 0.0, "STL/TOV": null, "TSA": 14.76, "2PA": 5.0, "college": "Indiana University", "FG": 6.0, "3PA": 8.0, "DRB": 1.0, "ORB%": 5.1, "BLK%": 0.0, "AST/TOV": null, "position": "SG", "AST": 4.0, "FT%": 0.5, "3PAr": 0.6153846153846154, "PF": 0.0, "PTS": 18.0, "FGA": 13.0, "DRBr": 0.5, "ORBr": 0.5, "2P": 2.0, "STL": 1.0, "TRB": 2.0, "TOV%": 0.0, "AST%": 24.6, "FTAr": 0.3076923076923077, "FTA": 4.0, "FIC": 13.5, "eFG%": 0.6153846153846154, "BLK": 0.0, "birth_date": "1988-12-25", "FG%": 0.46153846153846156, "2PAr": 0.38461538461538464, "FTr": 0.308, "+/-": 6.0, "name": "Eric Gordon", "USG%": 27.2, "DRB%": 3.7, "TS%": 0.6097560975609756, "experience": 8, "height": 1.9507437210436478, "2P%": 0.4, "MP": 23.716666666666665, "DRtg": 118.0, "ORtg": 139.0, "TRB%": 4.3, "FT/FGA": 0.15384615384615385, "ORB": 1.0, "3P%": 0.5, "HOB": 0.2222222222222222}, "Tyler Ennis": {"STL%": 0.0, "": "ca", "FT": 0.0, "weight": "194", "3P": 0.0, "TOV": 1.0, "STL/TOV": 0.0, "TSA": 2.0, "2PA": 2.0, "college": "Syracuse University", "FG": 0.0, "3PA": 0.0, "DRB": 0.0, "ORB%": 0.0, "BLK%": 0.0, "AST/TOV": 0.0, "position": "PG", "AST": 0.0, "FT%": null, "3PAr": 0.0, "PF": 0.0, "PTS": 0.0, "FGA": 2.0, "DRBr": null, "ORBr": null, "2P": 0.0, "STL": 0.0, "TRB": 0.0, "TOV%": 33.3, "AST%": 0.0, "FTAr": 0.0, "FTA": 0.0, "FIC": -2.5, "eFG%": 0.0, "BLK": 0.0, "birth_date": "1994-08-24", "FG%": 0.0, "2PAr": 1.0, "FTr": 0.0, "+/-": -2.0, "name": "Tyler Ennis", "USG%": 33.9, "DRB%": 0.0, "TS%": 0.0, "experience": 2, "height": 1.9202633504023408, "2P%": 0.0, "MP": 3.8666666666666667, "DRtg": 124.0, "ORtg": 0.0, "TRB%": 0.0, "FT/FGA": 0.0, "ORB": 0.0, "3P%": null, "HOB": 0.0}, "James Harden": {"STL%": 1.5, "": "us", "FT": 7.0, "weight": "220", "3P": 1.0, "TOV": 5.0, "STL/TOV": 0.2, "TSA": 19.52, "2PA": 11.0, "college": "Arizona State University", "FG": 6.0, "3PA": 5.0, "DRB": 6.0, "ORB%": 3.6, "BLK%": 2.0, "AST/TOV": 1.8, "position": "PG", "AST": 9.0, "FT%": 0.875, "3PAr": 0.3125, "PF": 3.0, "PTS": 20.0, "FGA": 16.0, "DRBr": 0.8571428571428571, "ORBr": 0.14285714285714285, "2P": 5.0, "STL": 1.0, "TRB": 7.0, "TOV%": 20.4, "AST%": 35.8, "FTAr": 0.5, "FTA": 8.0, "FIC": 15.0, "eFG%": 0.40625, "BLK": 1.0, "birth_date": "1989-08-26", "FG%": 0.375, "2PAr": 0.6875, "FTr": 0.5, "+/-": 12.0, "name": "James Harden", "USG%": 32.2, "DRB%": 15.7, "TS%": 0.5122950819672131, "experience": 7, "height": 1.9812240916849548, "2P%": 0.45454545454545453, "MP": 33.25, "DRtg": 110.0, "ORtg": 107.0, "TRB%": 10.6, "FT/FGA": 0.4375, "ORB": 1.0, "3P%": 0.2, "HOB": 0.3333333333333333}, "K.J. McDaniels": {"STL%": 0.0, "": "us", "FT": 0.0, "weight": "205", "3P": 0.0, "TOV": 0.0, "STL/TOV": null, "TSA": 3.0, "2PA": 3.0, "college": "Clemson University", "FG": 1.0, "3PA": 0.0, "DRB": 0.0, "ORB%": 0.0, "BLK%": 0.0, "AST/TOV": null, "position": "SF", "AST": 0.0, "FT%": null, "3PAr": 0.0, "PF": 0.0, "PTS": 2.0, "FGA": 3.0, "DRBr": null, "ORBr": null, "2P": 1.0, "STL": 0.0, "TRB": 0.0, "TOV%": 0.0, "AST%": 0.0, "FTAr": 0.0, "FTA": 0.0, "FIC": -0.25, "eFG%": 0.3333333333333333, "BLK": 0.0, "birth_date": "1993-02-09", "FG%": 0.3333333333333333, "2PAr": 1.0, "FTr": 0.0, "+/-": -4.0, "name": "K.J. McDaniels", "USG%": 29.6, "DRB%": 0.0, "TS%": 0.3333333333333333, "experience": 2, "height": 2.0117044623262617, "2P%": 0.3333333333333333, "MP": 4.416666666666667, "DRtg": 124.0, "ORtg": 72.0, "TRB%": 0.0, "FT/FGA": 0.0, "ORB": 0.0, "3P%": null, "HOB": 0.022222222222222223}, "Ryan Anderson": {"STL%": 2.0, "": "us", "FT": 6.0, "weight": "240", "3P": 4.0, "TOV": 0.0, "STL/TOV": null, "TSA": 9.64, "2PA": 1.0, "college": "University of California", "FG": 4.0, "3PA": 6.0, "DRB": 4.0, "ORB%": 9.8, "BLK%": 0.0, "AST/TOV": null, "position": "PF", "AST": 2.0, "FT%": 1.0, "3PAr": 0.8571428571428571, "PF": 3.0, "PTS": 18.0, "FGA": 7.0, "DRBr": 0.6666666666666666, "ORBr": 0.3333333333333333, "2P": 0.0, "STL": 1.0, "TRB": 6.0, "TOV%": 0.0, "AST%": 10.5, "FTAr": 0.8571428571428571, "FTA": 6.0, "FIC": 17.0, "eFG%": 0.8571428571428571, "BLK": 0.0, "birth_date": "1988-05-06", "FG%": 0.5714285714285714, "2PAr": 0.14285714285714285, "FTr": 0.857, "+/-": 14.0, "name": "Ryan Anderson", "USG%": 17.2, "DRB%": 14.2, "TS%": 0.933609958506224, "experience": 8, "height": 1.8593026091197267, "2P%": 0.0, "MP": 24.516666666666666, "DRtg": 111.0, "ORtg": 199.0, "TRB%": 12.4, "FT/FGA": 0.8571428571428571, "ORB": 2.0, "3P%": 0.6666666666666666, "HOB": 0.13333333333333333}, "Kyle Wiltjer": {"STL%": 0.0, "": "us", "FT": 0.0, "weight": "240", "3P": 1.0, "TOV": 0.0, "STL/TOV": null, "TSA": 1.0, "2PA": 0.0, "college": "Gonzaga University", "FG": 1.0, "3PA": 1.0, "DRB": 1.0, "ORB%": 0.0, "BLK%": 0.0, "AST/TOV": null, "position": "PF", "AST": 0.0, "FT%": null, "3PAr": 1.0, "PF": 0.0, "PTS": 3.0, "FGA": 1.0, "DRBr": 1.0, "ORBr": 0.0, "2P": 0.0, "STL": 0.0, "TRB": 1.0, "TOV%": 0.0, "AST%": 0.0, "FTAr": 0.0, "FTA": 0.0, "FIC": 3.0, "eFG%": 1.5, "BLK": 0.0, "birth_date": "1992-10-20", "FG%": 1.0, "2PAr": 0.0, "FTr": 0.0, "+/-": -2.0, "name": "Kyle Wiltjer", "USG%": 10.8, "DRB%": 21.5, "TS%": 1.5, "experience": 0, "height": 1.8593026091197267, "2P%": null, "MP": 4.05, "DRtg": 112.0, "ORtg": 300.0, "TRB%": 12.5, "FT/FGA": 0.0, "ORB": 0.0, "3P%": 1.0, "HOB": 0.022222222222222223}, "Corey Brewer": {"STL%": 3.9, "": "us", "FT": 0.0, "weight": "186", "3P": 0.0, "TOV": 1.0, "STL/TOV": 1.0, "TSA": 1.0, "2PA": 1.0, "college": "University of Florida", "FG": 1.0, "3PA": 0.0, "DRB": 0.0, "ORB%": 0.0, "BLK%": 0.0, "AST/TOV": 1.0, "position": "SF", "AST": 1.0, "FT%": null, "3PAr": 0.0, "PF": 1.0, "PTS": 2.0, "FGA": 1.0, "DRBr": null, "ORBr": null, "2P": 1.0, "STL": 1.0, "TRB": 0.0, "TOV%": 50.0, "AST%": 9.3, "FTAr": 0.0, "FTA": 0.0, "FIC": 1.75, "eFG%": 1.0, "BLK": 0.0, "birth_date": "1986-03-05", "FG%": 1.0, "2PAr": 1.0, "FTr": 0.0, "+/-": 8.0, "name": "Corey Brewer", "USG%": 7.0, "DRB%": 0.0, "TS%": 1.0, "experience": 9, "height": 2.103145574250183, "2P%": 1.0, "MP": 12.516666666666667, "DRtg": 115.0, "ORtg": 104.0, "TRB%": 0.0, "FT/FGA": 0.0, "ORB": 0.0, "3P%": null, "HOB": 0.044444444444444446}, "Clint Capela": {"STL%": 0.0, "": "ch", "FT": 1.0, "weight": "240", "3P": 0.0, "TOV": 2.0, "STL/TOV": 0.0, "TSA": 8.44, "2PA": 8.0, "college": "", "FG": 6.0, "3PA": 0.0, "DRB": 7.0, "ORB%": 9.2, "BLK%": 2.5, "AST/TOV": 0.5, "position": "C", "AST": 1.0, "FT%": 1.0, "3PAr": 0.0, "PF": 3.0, "PTS": 13.0, "FGA": 8.0, "DRBr": 0.7777777777777778, "ORBr": 0.2222222222222222, "2P": 6.0, "STL": 0.0, "TRB": 9.0, "TOV%": 19.2, "AST%": 5.4, "FTAr": 0.125, "FTA": 1.0, "FIC": 12.375, "eFG%": 0.75, "BLK": 1.0, "birth_date": "1994-05-18", "FG%": 0.75, "2PAr": 1.0, "FTr": 0.125, "+/-": 10.0, "name": "Clint Capela", "USG%": 17.5, "DRB%": 23.5, "TS%": 0.7701421800947867, "experience": 2, "height": 1.8593026091197267, "2P%": 0.75, "MP": 26.016666666666666, "DRtg": 108.0, "ORtg": 130.0, "TRB%": 17.5, "FT/FGA": 0.125, "ORB": 2.0, "3P%": null, "HOB": 0.15555555555555556}, "Patrick Beverley": {"STL%": 1.7, "": "us", "FT": 1.0, "weight": "185", "3P": 2.0, "TOV": 1.0, "STL/TOV": 1.0, "TSA": 9.88, "2PA": 4.0, "college": "University of Arkansas", "FG": 4.0, "3PA": 5.0, "DRB": 2.0, "ORB%": 4.2, "BLK%": 4.6, "AST/TOV": 5.0, "position": "SG", "AST": 5.0, "FT%": 0.5, "3PAr": 0.5555555555555556, "PF": 2.0, "PTS": 11.0, "FGA": 9.0, "DRBr": 0.6666666666666666, "ORBr": 0.3333333333333333, "2P": 2.0, "STL": 1.0, "TRB": 3.0, "TOV%": 9.2, "AST%": 22.2, "FTAr": 0.2222222222222222, "FTA": 2.0, "FIC": 12.0, "eFG%": 0.5555555555555556, "BLK": 2.0, "birth_date": "1988-07-12", "FG%": 0.4444444444444444, "2PAr": 0.4444444444444444, "FTr": 0.222, "+/-": 23.0, "name": "Patrick Beverley", "USG%": 16.8, "DRB%": 6.2, "TS%": 0.5566801619433198, "experience": 4, "height": 1.8593026091197267, "2P%": 0.5, "MP": 28.283333333333335, "DRtg": 114.0, "ORtg": 127.0, "TRB%": 5.4, "FT/FGA": 0.1111111111111111, "ORB": 1.0, "3P%": 0.4, "HOB": 0.2}, "Sam Dekker": {"STL%": 1.8, "": "us", "FT": 4.0, "weight": "230", "3P": 1.0, "TOV": 0.0, "STL/TOV": null, "TSA": 11.76, "2PA": 6.0, "college": "University of Wisconsin", "FG": 6.0, "3PA": 4.0, "DRB": 2.0, "ORB%": 4.4, "BLK%": 2.4, "AST/TOV": null, "position": "SF", "AST": 0.0, "FT%": 1.0, "3PAr": 0.4, "PF": 0.0, "PTS": 17.0, "FGA": 10.0, "DRBr": 0.6666666666666666, "ORBr": 0.3333333333333333, "2P": 5.0, "STL": 1.0, "TRB": 3.0, "TOV%": 0.0, "AST%": 0.0, "FTAr": 0.4, "FTA": 4.0, "FIC": 12.5, "eFG%": 0.65, "BLK": 1.0, "birth_date": "1994-05-06", "FG%": 0.6, "2PAr": 0.6, "FTr": 0.4, "+/-": 3.0, "name": "Sam Dekker", "USG%": 18.6, "DRB%": 6.3, "TS%": 0.7227891156462585, "experience": 1, "height": 2.103145574250183, "2P%": 0.8333333333333334, "MP": 27.533333333333335, "DRtg": 116.0, "ORtg": 154.0, "TRB%": 5.5, "FT/FGA": 0.4, "ORB": 1.0, "3P%": 0.25, "HOB": 0.13333333333333333}}, "scores": {"1": "42", "3": "26", "2": "31", "4": "29", "T": "128"}, "name": "Houston Rockets", "totals": {"STL%": 11.2, "FT": 21.0, "2PA": 51.0, "FG": 45.0, "DRB": 31.0, "ORB%": 25.0, "AST": 25.0, "3PAr": 0.42045454545454547, "PF": 14.0, "FGA": 88.0, "DRBr": 0.7560975609756098, "2P": 28.0, "ORBr": 0.24390243902439024, "TOV%": 10.0, "AST%": 55.6, "FTAr": 0.2840909090909091, "FIC": 110.875, "eFG%": 0.6079545454545454, "FG%": 0.5113636363636364, "2PAr": 0.5795454545454546, "+/-": 18.0, "USG%": 100.0, "DRtg": 111.8, "2P%": 0.5490196078431373, "DRB%": 56.4, "ORtg": 130.1, "TRB%": 43.2, "ORB": 10.0, "3P": 17.0, "TOV": 11.0, "STL/TOV": 1.0, "TSA": 99.0, "AST/TOV": 2.272727272727273, "3PA": 37.0, "BLK%": 9.6, "FT%": 0.84, "PTS": 128.0, "HOB": 1.5555555555555556, "STL": 11.0, "TRB": 41.0, "FTA": 25.0, "BLK": 7.0, "FTr": 0.284, "TS%": 0.6464646464646465, "FT/FGA": 0.23863636363636365, "3P%": 0.4594594594594595}}, "time": "22:30:00", "country": "United States", "date": "2016-12-02", "home": {"players": {"Jameer Nelson": {"STL%": 0.0, "": "us", "FT": 0.0, "weight": "190", "3P": 1.0, "TOV": 2.0, "STL/TOV": 0.0, "TSA": 5.0, "2PA": 2.0, "college": "Saint Joseph's University", "FG": 2.0, "3PA": 3.0, "DRB": 1.0, "ORB%": 0.0, "BLK%": 0.0, "AST/TOV": 1.0, "position": "PG", "AST": 2.0, "FT%": null, "3PAr": 0.6, "PF": 3.0, "PTS": 5.0, "FGA": 5.0, "DRBr": 1.0, "ORBr": 0.0, "2P": 1.0, "STL": 0.0, "TRB": 1.0, "TOV%": 28.6, "AST%": 12.7, "FTAr": 0.0, "FTA": 0.0, "FIC": 0.5, "eFG%": 0.5, "BLK": 0.0, "birth_date": "1982-02-09", "FG%": 0.4, "2PAr": 0.4, "FTr": 0.0, "+/-": -2.0, "name": "Jameer Nelson", "USG%": 14.2, "DRB%": 6.5, "TS%": 0.5, "experience": 12, "height": 1.8288222384784198, "2P%": 0.5, "MP": 18.583333333333332, "DRtg": 136.0, "ORtg": 89.0, "TRB%": 2.7, "FT/FGA": 0.0, "ORB": 0.0, "3P%": 0.3333333333333333, "HOB": 0.08695652173913043}, "Malik Beasley": {"STL%": 11.0, "": "us", "FT": 0.0, "weight": "196", "3P": 1.0, "TOV": 0.0, "STL/TOV": null, "TSA": 3.0, "2PA": 1.0, "college": "Florida State University", "FG": 2.0, "3PA": 2.0, "DRB": 0.0, "ORB%": 0.0, "BLK%": 0.0, "AST/TOV": null, "position": "SG", "AST": 0.0, "FT%": null, "3PAr": 0.6666666666666666, "PF": 0.0, "PTS": 5.0, "FGA": 3.0, "DRBr": null, "ORBr": null, "2P": 1.0, "STL": 1.0, "TRB": 0.0, "TOV%": 0.0, "AST%": 0.0, "FTAr": 0.0, "FTA": 0.0, "FIC": 3.75, "eFG%": 0.8333333333333334, "BLK": 0.0, "birth_date": "1996-11-26", "FG%": 0.6666666666666666, "2PAr": 0.3333333333333333, "FTr": 0.0, "+/-": 4.0, "name": "Malik Beasley", "USG%": 25.7, "DRB%": 0.0, "TS%": 0.8333333333333334, "experience": 0, "height": 1.9812240916849548, "2P%": 1.0, "MP": 4.416666666666667, "DRtg": 111.0, "ORtg": 171.0, "TRB%": 0.0, "FT/FGA": 0.0, "ORB": 0.0, "3P%": 0.5, "HOB": 0.043478260869565216}, "Will Barton": {"STL%": 1.5, "": "us", "FT": 2.0, "weight": "175", "3P": 1.0, "TOV": 2.0, "STL/TOV": 0.5, "TSA": 18.2, "2PA": 12.0, "college": "University of Memphis", "FG": 7.0, "3PA": 4.0, "DRB": 5.0, "ORB%": 5.2, "BLK%": 0.0, "AST/TOV": 2.5, "position": "SG", "AST": 5.0, "FT%": 0.4, "3PAr": 0.25, "PF": 2.0, "PTS": 17.0, "FGA": 16.0, "DRBr": 0.7142857142857143, "ORBr": 0.2857142857142857, "2P": 6.0, "STL": 1.0, "TRB": 7.0, "TOV%": 9.9, "AST%": 19.9, "FTAr": 0.3125, "FTA": 5.0, "FIC": 11.875, "eFG%": 0.46875, "BLK": 0.0, "birth_date": "1991-01-06", "FG%": 0.4375, "2PAr": 0.75, "FTr": 0.313, "+/-": -23.0, "name": "Will Barton", "USG%": 22.8, "DRB%": 17.9, "TS%": 0.46703296703296704, "experience": 4, "height": 2.0117044623262617, "2P%": 0.5, "MP": 33.483333333333334, "DRtg": 130.0, "ORtg": 109.0, "TRB%": 10.6, "FT/FGA": 0.125, "ORB": 2.0, "3P%": 0.25, "HOB": 0.2608695652173913}, "Kenneth Faried": {"STL%": 0.0, "": "us", "FT": 2.0, "weight": "228", "3P": 0.0, "TOV": 1.0, "STL/TOV": 0.0, "TSA": 15.88, "2PA": 15.0, "college": "Morehead State University", "FG": 6.0, "3PA": 0.0, "DRB": 2.0, "ORB%": 34.6, "BLK%": 0.0, "AST/TOV": 1.0, "position": "PF", "AST": 1.0, "FT%": 1.0, "3PAr": 0.0, "PF": 2.0, "PTS": 14.0, "FGA": 15.0, "DRBr": 0.18181818181818182, "ORBr": 0.8181818181818182, "2P": 6.0, "STL": 0.0, "TRB": 11.0, "TOV%": 5.9, "AST%": 6.3, "FTAr": 0.13333333333333333, "FTA": 2.0, "FIC": 11.5, "eFG%": 0.4, "BLK": 0.0, "birth_date": "1989-11-19", "FG%": 0.4, "2PAr": 1.0, "FTr": 0.133, "+/-": -13.0, "name": "Kenneth Faried", "USG%": 28.1, "DRB%": 10.6, "TS%": 0.44080604534005036, "experience": 5, "height": 2.0726652036088757, "2P%": 0.4, "MP": 22.716666666666665, "DRtg": 135.0, "ORtg": 118.0, "TRB%": 24.5, "FT/FGA": 0.13333333333333333, "ORB": 9.0, "3P%": null, "HOB": 0.15217391304347827}, "Danilo Gallinari": {"STL%": 0.0, "": "it", "FT": 2.0, "weight": "225", "3P": 2.0, "TOV": 1.0, "STL/TOV": 0.0, "TSA": 11.88, "2PA": 8.0, "college": "", "FG": 6.0, "3PA": 3.0, "DRB": 3.0, "ORB%": 5.1, "BLK%": 0.0, "AST/TOV": 1.0, "position": "SF", "AST": 1.0, "FT%": 1.0, "3PAr": 0.2727272727272727, "PF": 1.0, "PTS": 16.0, "FGA": 11.0, "DRBr": 0.6, "ORBr": 0.4, "2P": 4.0, "STL": 0.0, "TRB": 5.0, "TOV%": 7.8, "AST%": 3.7, "FTAr": 0.18181818181818182, "FTA": 2.0, "FIC": 10.75, "eFG%": 0.6363636363636364, "BLK": 0.0, "birth_date": "1988-08-08", "FG%": 0.5454545454545454, "2PAr": 0.7272727272727273, "FTr": 0.182, "+/-": -16.0, "name": "Danilo Gallinari", "USG%": 14.1, "DRB%": 10.4, "TS%": 0.6734006734006733, "experience": 7, "height": 1.8593026091197267, "2P%": 0.5, "MP": 34.53333333333333, "DRtg": 135.0, "ORtg": 144.0, "TRB%": 7.3, "FT/FGA": 0.18181818181818182, "ORB": 2.0, "3P%": 0.6666666666666666, "HOB": 0.15217391304347827}, "Emmanuel Mudiay": {"STL%": 0.0, "": "cd", "FT": 2.0, "weight": "200", "3P": 1.0, "TOV": 1.0, "STL/TOV": 0.0, "TSA": 12.88, "2PA": 6.0, "college": "", "FG": 3.0, "3PA": 6.0, "DRB": 2.0, "ORB%": 3.0, "BLK%": 0.0, "AST/TOV": 5.0, "position": "PG", "AST": 5.0, "FT%": 1.0, "3PAr": 0.5, "PF": 4.0, "PTS": 9.0, "FGA": 12.0, "DRBr": 0.6666666666666666, "ORBr": 0.3333333333333333, "2P": 2.0, "STL": 0.0, "TRB": 3.0, "TOV%": 7.2, "AST%": 20.1, "FTAr": 0.16666666666666666, "FTA": 2.0, "FIC": 3.75, "eFG%": 0.2916666666666667, "BLK": 0.0, "birth_date": "1996-03-05", "FG%": 0.25, "2PAr": 0.5, "FTr": 0.167, "+/-": -20.0, "name": "Emmanuel Mudiay", "USG%": 18.0, "DRB%": 8.3, "TS%": 0.3493788819875776, "experience": 1, "height": 1.9812240916849548, "2P%": 0.3333333333333333, "MP": 29.083333333333332, "DRtg": 135.0, "ORtg": 103.0, "TRB%": 5.2, "FT/FGA": 0.16666666666666666, "ORB": 1.0, "3P%": 0.16666666666666666, "HOB": 0.17391304347826086}, "Jusuf Nurkic": {"STL%": 4.8, "": "ba", "FT": 0.0, "weight": "280", "3P": 0.0, "TOV": 4.0, "STL/TOV": 0.5, "TSA": 9.88, "2PA": 9.0, "college": "", "FG": 5.0, "3PA": 0.0, "DRB": 3.0, "ORB%": 17.1, "BLK%": 13.9, "AST/TOV": 0.25, "position": "C", "AST": 1.0, "FT%": 0.0, "3PAr": 0.0, "PF": 2.0, "PTS": 10.0, "FGA": 9.0, "DRBr": 0.42857142857142855, "ORBr": 0.5714285714285714, "2P": 5.0, "STL": 2.0, "TRB": 7.0, "TOV%": 28.8, "AST%": 6.9, "FTAr": 0.2222222222222222, "FTA": 2.0, "FIC": 9.75, "eFG%": 0.5555555555555556, "BLK": 3.0, "birth_date": "1994-08-23", "FG%": 0.5555555555555556, "2PAr": 1.0, "FTr": 0.222, "+/-": -21.0, "name": "Jusuf Nurkic", "USG%": 25.7, "DRB%": 17.7, "TS%": 0.5060728744939271, "experience": 2, "height": 2.13362594489149, "2P%": 0.5555555555555556, "MP": 20.366666666666667, "DRtg": 113.0, "ORtg": 84.0, "TRB%": 17.4, "FT/FGA": 0.0, "ORB": 4.0, "3P%": null, "HOB": 0.13043478260869565}, "Juan Hernangomez": {"STL%": 0.0, "": "es", "FT": 0.0, "weight": "230", "3P": 0.0, "TOV": 0.0, "STL/TOV": null, "TSA": 2.0, "2PA": 1.0, "college": "", "FG": 0.0, "3PA": 1.0, "DRB": 4.0, "ORB%": 0.0, "BLK%": 0.0, "AST/TOV": null, "position": "PF", "AST": 0.0, "FT%": null, "3PAr": 0.5, "PF": 0.0, "PTS": 0.0, "FGA": 2.0, "DRBr": 1.0, "ORBr": 0.0, "2P": 0.0, "STL": 0.0, "TRB": 4.0, "TOV%": 0.0, "AST%": 0.0, "FTAr": 0.0, "FTA": 0.0, "FIC": 1.5, "eFG%": 0.0, "BLK": 0.0, "birth_date": "1995-09-28", "FG%": 0.0, "2PAr": 0.5, "FTr": 0.0, "+/-": -2.0, "name": "Juan Hernangomez", "USG%": 9.7, "DRB%": 61.7, "TS%": 0.0, "experience": 0, "height": 2.103145574250183, "2P%": 0.0, "MP": 7.783333333333333, "DRtg": 123.0, "ORtg": 0.0, "TRB%": 26.0, "FT/FGA": 0.0, "ORB": 0.0, "3P%": 0.0, "HOB": 0.0}, "Mike Miller": {"STL%": 0.0, "": "us", "FT": 0.0, "weight": "218", "3P": 0.0, "TOV": 0.0, "STL/TOV": null, "TSA": 0.0, "2PA": 0.0, "college": "University of Florida", "FG": 0.0, "3PA": 0.0, "DRB": 2.0, "ORB%": 0.0, "BLK%": 0.0, "AST/TOV": null, "position": "SF", "AST": 2.0, "FT%": null, "3PAr": null, "PF": 0.0, "PTS": 0.0, "FGA": 0.0, "DRBr": 1.0, "ORBr": 0.0, "2P": 0.0, "STL": 0.0, "TRB": 2.0, "TOV%": null, "AST%": 51.5, "FTAr": null, "FTA": 0.0, "FIC": 3.5, "eFG%": null, "BLK": 0.0, "birth_date": "1980-02-19", "FG%": null, "2PAr": null, "FTr": null, "+/-": 2.0, "name": "Mike Miller", "USG%": 0.0, "DRB%": 59.3, "TS%": null, "experience": 16, "height": 2.0726652036088757, "2P%": null, "MP": 4.05, "DRtg": 124.0, "ORtg": 220.0, "TRB%": 25.0, "FT/FGA": null, "ORB": 0.0, "3P%": null, "HOB": 0.043478260869565216}, "Alonzo Gee": {"STL%": 0.0, "": "us", "FT": 0.0, "weight": "225", "3P": 0.0, "TOV": 0.0, "STL/TOV": null, "TSA": 1.0, "2PA": 1.0, "college": "University of Alabama", "FG": 0.0, "3PA": 0.0, "DRB": 1.0, "ORB%": 9.2, "BLK%": 0.0, "AST/TOV": null, "position": "SF", "AST": 1.0, "FT%": null, "3PAr": 0.0, "PF": 1.0, "PTS": 0.0, "FGA": 1.0, "DRBr": 0.5, "ORBr": 0.5, "2P": 0.0, "STL": 0.0, "TRB": 2.0, "TOV%": 0.0, "AST%": 11.0, "FTAr": 0.0, "FTA": 0.0, "FIC": 1.5, "eFG%": 0.0, "BLK": 0.0, "birth_date": "1987-05-29", "FG%": 0.0, "2PAr": 1.0, "FTr": 0.0, "+/-": 5.0, "name": "Alonzo Gee", "USG%": 4.0, "DRB%": 12.7, "TS%": 0.0, "experience": 7, "height": 2.0117044623262617, "2P%": 0.0, "MP": 9.45, "DRtg": 134.0, "ORtg": 95.0, "TRB%": 10.7, "FT/FGA": 0.0, "ORB": 1.0, "3P%": null, "HOB": 0.021739130434782608}, "Darrell Arthur": {"STL%": 0.0, "": "us", "FT": 0.0, "weight": "235", "3P": 0.0, "TOV": 1.0, "STL/TOV": 0.0, "TSA": 4.0, "2PA": 4.0, "college": "University of Kansas", "FG": 4.0, "3PA": 0.0, "DRB": 2.0, "ORB%": 19.1, "BLK%": 10.3, "AST/TOV": 1.0, "position": "PF", "AST": 1.0, "FT%": null, "3PAr": 0.0, "PF": 2.0, "PTS": 8.0, "FGA": 4.0, "DRBr": 0.5, "ORBr": 0.5, "2P": 4.0, "STL": 0.0, "TRB": 4.0, "TOV%": 20.0, "AST%": 21.1, "FTAr": 0.0, "FTA": 0.0, "FIC": 8.5, "eFG%": 1.0, "BLK": 1.0, "birth_date": "1988-03-25", "FG%": 1.0, "2PAr": 1.0, "FTr": 0.0, "+/-": 2.0, "name": "Darrell Arthur", "USG%": 20.7, "DRB%": 26.3, "TS%": 1.0, "experience": 7, "height": 2.103145574250183, "2P%": 1.0, "MP": 9.116666666666667, "DRtg": 124.0, "ORtg": 153.0, "TRB%": 22.2, "FT/FGA": 0.0, "ORB": 2.0, "3P%": null, "HOB": 0.10869565217391304}, "Wilson Chandler": {"STL%": 1.7, "": "us", "FT": 1.0, "weight": "225", "3P": 3.0, "TOV": 2.0, "STL/TOV": 0.5, "TSA": 20.32, "2PA": 12.0, "college": "DePaul University", "FG": 10.0, "3PA": 7.0, "DRB": 3.0, "ORB%": 6.0, "BLK%": 0.0, "AST/TOV": 1.0, "position": "SF", "AST": 2.0, "FT%": 0.3333333333333333, "3PAr": 0.3684210526315789, "PF": 1.0, "PTS": 24.0, "FGA": 19.0, "DRBr": 0.6, "ORBr": 0.4, "2P": 7.0, "STL": 1.0, "TRB": 5.0, "TOV%": 9.0, "AST%": 11.1, "FTAr": 0.15789473684210525, "FTA": 3.0, "FIC": 13.375, "eFG%": 0.6052631578947368, "BLK": 0.0, "birth_date": "1987-05-10", "FG%": 0.5263157894736842, "2PAr": 0.631578947368421, "FTr": 0.158, "+/-": -8.0, "name": "Wilson Chandler", "USG%": 28.8, "DRB%": 12.3, "TS%": 0.5905511811023622, "experience": 8, "height": 2.0726652036088757, "2P%": 0.5833333333333334, "MP": 29.283333333333335, "DRtg": 131.0, "ORtg": 123.0, "TRB%": 8.6, "FT/FGA": 0.05263157894736842, "ORB": 2.0, "3P%": 0.42857142857142855, "HOB": 0.2608695652173913}, "Jamal Murray": {"STL%": 0.0, "": "ca", "FT": 0.0, "weight": "207", "3P": 0.0, "TOV": 2.0, "STL/TOV": 0.0, "TSA": 7.0, "2PA": 2.0, "college": "University of Kentucky", "FG": 1.0, "3PA": 5.0, "DRB": 2.0, "ORB%": 5.1, "BLK%": 0.0, "AST/TOV": 0.5, "position": "SG", "AST": 1.0, "FT%": null, "3PAr": 0.7142857142857143, "PF": 2.0, "PTS": 2.0, "FGA": 7.0, "DRBr": 0.6666666666666666, "ORBr": 0.3333333333333333, "2P": 1.0, "STL": 0.0, "TRB": 3.0, "TOV%": 22.2, "AST%": 6.5, "FTAr": 0.0, "FTA": 0.0, "FIC": -2.75, "eFG%": 0.14285714285714285, "BLK": 0.0, "birth_date": "1997-02-23", "FG%": 0.14285714285714285, "2PAr": 0.2857142857142857, "FTr": 0.0, "+/-": 2.0, "name": "Jamal Murray", "USG%": 19.8, "DRB%": 14.0, "TS%": 0.14285714285714285, "experience": 0, "height": 1.9507437210436478, "2P%": 0.5, "MP": 17.133333333333333, "DRtg": 134.0, "ORtg": 41.0, "TRB%": 8.8, "FT/FGA": 0.0, "ORB": 1.0, "3P%": 0.0, "HOB": 0.043478260869565216}}, "scores": {"1": "33", "3": "21", "2": "30", "4": "26", "T": "110"}, "name": "Denver Nuggets", "totals": {"STL%": 5.1, "FT": 9.0, "2PA": 73.0, "FG": 46.0, "DRB": 30.0, "ORB%": 43.6, "AST": 22.0, "3PAr": 0.2980769230769231, "PF": 20.0, "FGA": 104.0, "DRBr": 0.5555555555555556, "2P": 37.0, "ORBr": 0.4444444444444444, "TOV%": 12.6, "AST%": 47.8, "FTAr": 0.15384615384615385, "FIC": 77.5, "eFG%": 0.4855769230769231, "FG%": 0.4423076923076923, "2PAr": 0.7019230769230769, "+/-": -18.0, "USG%": 100.0, "DRtg": 130.1, "2P%": 0.5068493150684932, "DRB%": 75.0, "ORtg": 111.8, "TRB%": 56.8, "ORB": 24.0, "3P": 9.0, "TOV": 16.0, "STL/TOV": 0.3125, "TSA": 111.04, "AST/TOV": 1.375, "3PA": 31.0, "BLK%": 7.8, "FT%": 0.5625, "PTS": 110.0, "HOB": 1.4782608695652173, "STL": 5.0, "TRB": 54.0, "FTA": 16.0, "BLK": 4.0, "FTr": 0.154, "TS%": 0.4953170028818443, "FT/FGA": 0.08653846153846154, "3P%": 0.2903225806451613}}, "type": "Season"}