{"league": "nba", "code": "201503040MIN", "season": "2014-2015", "away": {"players": {"Jameer Nelson": {"STL%": 2.1, "": "us", "FT": 0.0, "weight": "190", "3P": 0.0, "TOV": 3.0, "STL/TOV": 0.3333333333333333, "TSA": 10.0, "2PA": 7.0, "college": "Saint Joseph's University", "FG": 6.0, "3PA": 3.0, "DRB": 2.0, "ORB%": 0.0, "BLK%": 0.0, "AST/TOV": 3.0, "position": "PG", "AST": 9.0, "FT%": null, "3PAr": 0.3, "PF": 1.0, "PTS": 12.0, "FGA": 10.0, "DRBr": 1.0, "ORBr": 0.0, "2P": 6.0, "STL": 1.0, "TRB": 2.0, "TOV%": 23.1, "AST%": 55.7, "FTAr": 0.0, "FTA": 0.0, "FIC": 12.5, "eFG%": 0.6, "BLK": 0.0, "birth_date": "1982-02-09", "FG%": 0.6, "2PAr": 0.7, "FTr": 0.0, "+/-": 19.0, "name": "Jameer Nelson", "USG%": 22.5, "DRB%": 7.7, "TS%": 0.6, "experience": 10, "height": 1.8288222384784198, "2P%": 0.8571428571428571, "MP": 25.316666666666666, "DRtg": 96.0, "ORtg": 113.0, "TRB%": 4.0, "FT/FGA": 0.0, "ORB": 0.0, "3P%": 0.0, "HOB": 0.35714285714285715}, "Will Barton": {"STL%": 3.4, "": "us", "FT": 3.0, "weight": "175", "3P": 2.0, "TOV": 0.0, "STL/TOV": null, "TSA": 12.76, "2PA": 7.0, "college": "University of Memphis", "FG": 6.0, "3PA": 4.0, "DRB": 5.0, "ORB%": 3.5, "BLK%": 0.0, "AST/TOV": null, "position": "SG", "AST": 2.0, "FT%": 0.75, "3PAr": 0.36363636363636365, "PF": 3.0, "PTS": 17.0, "FGA": 11.0, "DRBr": 0.8333333333333334, "ORBr": 0.16666666666666666, "2P": 4.0, "STL": 2.0, "TRB": 6.0, "TOV%": 0.0, "AST%": 9.7, "FTAr": 0.36363636363636365, "FTA": 4.0, "FIC": 14.5, "eFG%": 0.6363636363636364, "BLK": 0.0, "birth_date": "1991-01-06", "FG%": 0.5454545454545454, "2PAr": 0.6363636363636364, "FTr": 0.364, "+/-": 15.0, "name": "Will Barton", "USG%": 18.4, "DRB%": 16.1, "TS%": 0.6661442006269592, "experience": 2, "height": 2.0117044623262617, "2P%": 0.5714285714285714, "MP": 30.416666666666668, "DRtg": 90.0, "ORtg": 146.0, "TRB%": 10.1, "FT/FGA": 0.2727272727272727, "ORB": 1.0, "3P%": 0.5, "HOB": 0.19047619047619047}, "Kenneth Faried": {"STL%": 3.2, "": "us", "FT": 2.0, "weight": "228", "3P": 0.0, "TOV": 3.0, "STL/TOV": 0.6666666666666666, "TSA": 15.32, "2PA": 14.0, "college": "Morehead State University", "FG": 8.0, "3PA": 0.0, "DRB": 10.0, "ORB%": 13.0, "BLK%": 4.6, "AST/TOV": 0.6666666666666666, "position": "PF", "AST": 2.0, "FT%": 0.6666666666666666, "3PAr": 0.0, "PF": 3.0, "PTS": 18.0, "FGA": 14.0, "DRBr": 0.7142857142857143, "ORBr": 0.2857142857142857, "2P": 8.0, "STL": 2.0, "TRB": 14.0, "TOV%": 16.4, "AST%": 9.6, "FTAr": 0.21428571428571427, "FTA": 3.0, "FIC": 19.375, "eFG%": 0.5714285714285714, "BLK": 2.0, "birth_date": "1989-11-19", "FG%": 0.5714285714285714, "2PAr": 1.0, "FTr": 0.214, "+/-": 10.0, "name": "Kenneth Faried", "USG%": 24.4, "DRB%": 29.8, "TS%": 0.5874673629242819, "experience": 3, "height": 2.0726652036088757, "2P%": 0.5714285714285714, "MP": 32.88333333333333, "DRtg": 82.0, "ORtg": 109.0, "TRB%": 21.7, "FT/FGA": 0.14285714285714285, "ORB": 4.0, "3P%": null, "HOB": 0.23809523809523808}, "Danilo Gallinari": {"STL%": 1.6, "": "it", "FT": 3.0, "weight": "225", "3P": 3.0, "TOV": 0.0, "STL/TOV": null, "TSA": 11.32, "2PA": 4.0, "college": "", "FG": 5.0, "3PA": 6.0, "DRB": 4.0, "ORB%": 3.3, "BLK%": 0.0, "AST/TOV": null, "position": "SF", "AST": 3.0, "FT%": 1.0, "3PAr": 0.6, "PF": 2.0, "PTS": 16.0, "FGA": 10.0, "DRBr": 0.8, "ORBr": 0.2, "2P": 2.0, "STL": 1.0, "TRB": 5.0, "TOV%": 0.0, "AST%": 12.9, "FTAr": 0.3, "FTA": 3.0, "FIC": 14.375, "eFG%": 0.65, "BLK": 0.0, "birth_date": "1988-08-08", "FG%": 0.5, "2PAr": 0.4, "FTr": 0.3, "+/-": -6.0, "name": "Danilo Gallinari", "USG%": 15.4, "DRB%": 12.1, "TS%": 0.7067137809187279, "experience": 5, "height": 1.8593026091197267, "2P%": 0.5, "MP": 32.28333333333333, "DRtg": 95.0, "ORtg": 158.0, "TRB%": 7.9, "FT/FGA": 0.3, "ORB": 1.0, "3P%": 0.5, "HOB": 0.19047619047619047}, "Joffrey Lauvergne": {"STL%": 0.0, "": "fr", "FT": 0.0, "weight": "220", "3P": 0.0, "TOV": 0.0, "STL/TOV": null, "TSA": 8.0, "2PA": 8.0, "college": "", "FG": 3.0, "3PA": 0.0, "DRB": 2.0, "ORB%": 19.9, "BLK%": 0.0, "AST/TOV": null, "position": "C", "AST": 0.0, "FT%": null, "3PAr": 0.0, "PF": 2.0, "PTS": 6.0, "FGA": 8.0, "DRBr": 0.5, "ORBr": 0.5, "2P": 3.0, "STL": 0.0, "TRB": 4.0, "TOV%": 0.0, "AST%": 0.0, "FTAr": 0.0, "FTA": 0.0, "FIC": 2.5, "eFG%": 0.375, "BLK": 0.0, "birth_date": "1991-09-30", "FG%": 0.375, "2PAr": 1.0, "FTr": 0.0, "+/-": 15.0, "name": "Joffrey Lauvergne", "USG%": 32.7, "DRB%": 18.3, "TS%": 0.375, "experience": 0, "height": 1.8623506461838577, "2P%": 0.375, "MP": 10.733333333333333, "DRtg": 96.0, "ORtg": 93.0, "TRB%": 19.0, "FT/FGA": 0.0, "ORB": 2.0, "3P%": null, "HOB": 0.07142857142857142}, "Ty Lawson": {"STL%": 2.1, "": "us", "FT": 0.0, "weight": "195", "3P": 0.0, "TOV": 1.0, "STL/TOV": 1.0, "TSA": 9.0, "2PA": 8.0, "college": "University of North Carolina", "FG": 0.0, "3PA": 1.0, "DRB": 4.0, "ORB%": 12.8, "BLK%": 0.0, "AST/TOV": 9.0, "position": "PG", "AST": 9.0, "FT%": null, "3PAr": 0.1111111111111111, "PF": 3.0, "PTS": 0.0, "FGA": 9.0, "DRBr": 0.5714285714285714, "ORBr": 0.42857142857142855, "2P": 0.0, "STL": 1.0, "TRB": 7.0, "TOV%": 10.0, "AST%": 41.3, "FTAr": 0.0, "FTA": 0.0, "FIC": 6.75, "eFG%": 0.0, "BLK": 0.0, "birth_date": "1987-11-03", "FG%": 0.0, "2PAr": 0.8888888888888888, "FTr": 0.0, "+/-": -4.0, "name": "Ty Lawson", "USG%": 17.6, "DRB%": 15.7, "TS%": 0.0, "experience": 5, "height": 1.5575469397707877, "2P%": 0.0, "MP": 24.916666666666668, "DRtg": 92.0, "ORtg": 67.0, "TRB%": 14.3, "FT/FGA": 0.0, "ORB": 3.0, "3P%": 0.0, "HOB": 0.21428571428571427}, "Jusuf Nurkic": {"": "ba", "name": "Jusuf Nurkic", "weight": "280", "experience": 0, "height": 2.13362594489149, "college": "", "MP": 0.0, "birth_date": "1994-08-23", "position": "C"}, "Randy Foye": {"STL%": 0.0, "": "us", "FT": 0.0, "weight": "213", "3P": 2.0, "TOV": 2.0, "STL/TOV": 0.0, "TSA": 7.0, "2PA": 5.0, "college": "Villanova University", "FG": 4.0, "3PA": 2.0, "DRB": 2.0, "ORB%": 0.0, "BLK%": 0.0, "AST/TOV": 0.5, "position": "SG", "AST": 1.0, "FT%": null, "3PAr": 0.2857142857142857, "PF": 0.0, "PTS": 10.0, "FGA": 7.0, "DRBr": 1.0, "ORBr": 0.0, "2P": 2.0, "STL": 0.0, "TRB": 2.0, "TOV%": 22.2, "AST%": 8.8, "FTAr": 0.0, "FTA": 0.0, "FIC": 5.25, "eFG%": 0.7142857142857143, "BLK": 0.0, "birth_date": "1983-09-24", "FG%": 0.5714285714285714, "2PAr": 0.7142857142857143, "FTr": 0.0, "+/-": 0.0, "name": "Randy Foye", "USG%": 22.5, "DRB%": 11.1, "TS%": 0.7142857142857143, "experience": 8, "height": 1.9507437210436478, "2P%": 0.4, "MP": 17.583333333333332, "DRtg": 99.0, "ORtg": 104.0, "TRB%": 5.8, "FT/FGA": 0.0, "ORB": 0.0, "3P%": 1.0, "HOB": 0.11904761904761904}, "J.J. Hickson": {"STL%": 3.8, "": "us", "FT": 0.0, "weight": "242", "3P": 0.0, "TOV": 1.0, "STL/TOV": 1.0, "TSA": 6.0, "2PA": 6.0, "college": "North Carolina State University", "FG": 3.0, "3PA": 0.0, "DRB": 2.0, "ORB%": 0.0, "BLK%": 5.5, "AST/TOV": 0.0, "position": "C", "AST": 0.0, "FT%": null, "3PAr": 0.0, "PF": 3.0, "PTS": 6.0, "FGA": 6.0, "DRBr": 1.0, "ORBr": 0.0, "2P": 3.0, "STL": 1.0, "TRB": 2.0, "TOV%": 14.3, "AST%": 0.0, "FTAr": 0.0, "FTA": 0.0, "FIC": 2.5, "eFG%": 0.5, "BLK": 1.0, "birth_date": "1988-09-04", "FG%": 0.5, "2PAr": 1.0, "FTr": 0.0, "+/-": 2.0, "name": "J.J. Hickson", "USG%": 22.5, "DRB%": 14.3, "TS%": 0.5, "experience": 6, "height": 2.103145574250183, "2P%": 0.5, "MP": 13.666666666666666, "DRtg": 85.0, "ORtg": 84.0, "TRB%": 7.5, "FT/FGA": 0.0, "ORB": 0.0, "3P%": null, "HOB": 0.07142857142857142}, "Erick Green": {"STL%": 0.0, "": "us", "FT": 0.0, "weight": "185", "3P": 0.0, "TOV": 0.0, "STL/TOV": null, "TSA": 0.0, "2PA": 0.0, "college": "Virginia Polytechnic Institute and State University", "FG": 0.0, "3PA": 0.0, "DRB": 0.0, "ORB%": 0.0, "BLK%": 0.0, "AST/TOV": null, "position": "PG", "AST": 0.0, "FT%": null, "3PAr": null, "PF": 0.0, "PTS": 0.0, "FGA": 0.0, "DRBr": null, "ORBr": null, "2P": 0.0, "STL": 0.0, "TRB": 0.0, "TOV%": null, "AST%": 0.0, "FTAr": null, "FTA": 0.0, "FIC": 0.0, "eFG%": null, "BLK": 0.0, "birth_date": "1991-05-09", "FG%": null, "2PAr": null, "FTr": null, "+/-": 0.0, "name": "Erick Green", "USG%": 0.0, "DRB%": 0.0, "TS%": null, "experience": 0, "height": 1.9507437210436478, "2P%": null, "MP": 2.3, "DRtg": 103.0, "ORtg": 0.0, "TRB%": 0.0, "FT/FGA": null, "ORB": 0.0, "3P%": null, "HOB": 0.0}, "Darrell Arthur": {"STL%": 0.0, "": "us", "FT": 0.0, "weight": "235", "3P": 0.0, "TOV": 1.0, "STL/TOV": 0.0, "TSA": 4.0, "2PA": 4.0, "college": "University of Kansas", "FG": 3.0, "3PA": 0.0, "DRB": 0.0, "ORB%": 0.0, "BLK%": 0.0, "AST/TOV": 0.0, "position": "PF", "AST": 0.0, "FT%": null, "3PAr": 0.0, "PF": 1.0, "PTS": 6.0, "FGA": 4.0, "DRBr": null, "ORBr": null, "2P": 3.0, "STL": 0.0, "TRB": 0.0, "TOV%": 20.0, "AST%": 0.0, "FTAr": 0.0, "FTA": 0.0, "FIC": 1.5, "eFG%": 0.75, "BLK": 0.0, "birth_date": "1988-03-25", "FG%": 0.75, "2PAr": 1.0, "FTr": 0.0, "+/-": 11.0, "name": "Darrell Arthur", "USG%": 14.7, "DRB%": 0.0, "TS%": 0.75, "experience": 5, "height": 2.103145574250183, "2P%": 0.75, "MP": 14.966666666666667, "DRtg": 103.0, "ORtg": 107.0, "TRB%": 0.0, "FT/FGA": 0.0, "ORB": 0.0, "3P%": null, "HOB": 0.07142857142857142}, "Wilson Chandler": {"STL%": 0.0, "": "us", "FT": 0.0, "weight": "225", "3P": 1.0, "TOV": 2.0, "STL/TOV": 0.0, "TSA": 10.0, "2PA": 7.0, "college": "DePaul University", "FG": 4.0, "3PA": 3.0, "DRB": 4.0, "ORB%": 12.2, "BLK%": 0.0, "AST/TOV": 0.5, "position": "SF", "AST": 1.0, "FT%": null, "3PAr": 0.3, "PF": 1.0, "PTS": 9.0, "FGA": 10.0, "DRBr": 0.5714285714285714, "ORBr": 0.42857142857142855, "2P": 3.0, "STL": 0.0, "TRB": 7.0, "TOV%": 16.7, "AST%": 5.3, "FTAr": 0.0, "FTA": 0.0, "FIC": 6.0, "eFG%": 0.45, "BLK": 0.0, "birth_date": "1987-05-10", "FG%": 0.4, "2PAr": 0.7, "FTr": 0.0, "+/-": 10.0, "name": "Wilson Chandler", "USG%": 20.1, "DRB%": 15.0, "TS%": 0.45, "experience": 7, "height": 2.0726652036088757, "2P%": 0.42857142857142855, "MP": 26.2, "DRtg": 97.0, "ORtg": 91.0, "TRB%": 13.6, "FT/FGA": 0.0, "ORB": 3.0, "3P%": 0.3333333333333333, "HOB": 0.11904761904761904}, "Gary Harris": {"STL%": 0.0, "": "us", "FT": 0.0, "weight": "210", "3P": 0.0, "TOV": 0.0, "STL/TOV": null, "TSA": 3.0, "2PA": 2.0, "college": "Michigan State University", "FG": 0.0, "3PA": 1.0, "DRB": 2.0, "ORB%": 0.0, "BLK%": 0.0, "AST/TOV": null, "position": "SG", "AST": 0.0, "FT%": null, "3PAr": 0.3333333333333333, "PF": 2.0, "PTS": 0.0, "FGA": 3.0, "DRBr": 1.0, "ORBr": 0.0, "2P": 0.0, "STL": 0.0, "TRB": 2.0, "TOV%": 0.0, "AST%": 0.0, "FTAr": 0.0, "FTA": 0.0, "FIC": -1.75, "eFG%": 0.0, "BLK": 0.0, "birth_date": "1994-09-14", "FG%": 0.0, "2PAr": 0.6666666666666666, "FTr": 0.0, "+/-": 3.0, "name": "Gary Harris", "USG%": 15.1, "DRB%": 22.4, "TS%": 0.0, "experience": 0, "height": 1.9507437210436478, "2P%": 0.0, "MP": 8.733333333333333, "DRtg": 94.0, "ORtg": 0.0, "TRB%": 11.7, "FT/FGA": 0.0, "ORB": 0.0, "3P%": 0.0, "HOB": 0.0}}, "scores": {"1": "26", "3": "17", "2": "34", "4": "23", "T": "100"}, "name": "Denver Nuggets", "totals": {"STL%": 8.7, "FT": 8.0, "2PA": 72.0, "FG": 42.0, "DRB": 37.0, "ORB%": 31.1, "AST": 27.0, "3PAr": 0.21739130434782608, "PF": 21.0, "FGA": 92.0, "DRBr": 0.7254901960784313, "2P": 34.0, "ORBr": 0.27450980392156865, "TOV%": 11.9, "AST%": 64.3, "FTAr": 0.10869565217391304, "FIC": 83.5, "eFG%": 0.5, "FG%": 0.45652173913043476, "2PAr": 0.782608695652174, "+/-": 15.0, "USG%": 100.0, "DRtg": 92.8, "2P%": 0.4722222222222222, "DRB%": 75.5, "ORtg": 109.1, "TRB%": 54.3, "ORB": 14.0, "3P": 8.0, "TOV": 13.0, "STL/TOV": 0.6153846153846154, "TSA": 96.4, "AST/TOV": 2.076923076923077, "3PA": 20.0, "BLK%": 4.7, "FT%": 0.8, "PTS": 100.0, "HOB": 1.6428571428571428, "STL": 8.0, "TRB": 51.0, "FTA": 10.0, "BLK": 3.0, "FTr": 0.109, "TS%": 0.5186721991701244, "FT/FGA": 0.08695652173913043, "3P%": 0.4}}, "time": "20:00:00", "country": "United States", "date": "2015-03-04", "home": {"players": {"Zach LaVine": {"STL%": 0.0, "": "us", "FT": 0.0, "weight": "189", "3P": 1.0, "TOV": 2.0, "STL/TOV": 0.0, "TSA": 4.0, "2PA": 1.0, "college": "University of California, Los Angeles", "FG": 1.0, "3PA": 3.0, "DRB": 1.0, "ORB%": 9.8, "BLK%": 0.0, "AST/TOV": 0.5, "position": "PG", "AST": 1.0, "FT%": null, "3PAr": 0.75, "PF": 2.0, "PTS": 3.0, "FGA": 4.0, "DRBr": 0.5, "ORBr": 0.5, "2P": 0.0, "STL": 0.0, "TRB": 2.0, "TOV%": 33.3, "AST%": 17.8, "FTAr": 0.0, "FTA": 0.0, "FIC": -0.25, "eFG%": 0.375, "BLK": 0.0, "birth_date": "1995-03-10", "FG%": 0.25, "2PAr": 0.25, "FTr": 0.0, "+/-": -8.0, "name": "Zach LaVine", "USG%": 27.6, "DRB%": 10.7, "TS%": 0.375, "experience": 0, "height": 1.9812240916849548, "2P%": 0.0, "MP": 9.95, "DRtg": 115.0, "ORtg": 63.0, "TRB%": 10.3, "FT/FGA": 0.0, "ORB": 1.0, "3P%": 0.3333333333333333, "HOB": 0.0625}, "Lorenzo Brown": {"": "us", "name": "Lorenzo Brown", "weight": "189", "experience": 1, "height": 1.9812240916849548, "college": "North Carolina State University", "MP": 0.0, "birth_date": "1990-08-26", "position": "PG"}, "Nikola Pekovic": {"STL%": 6.8, "": "me", "FT": 2.0, "weight": "307", "3P": 0.0, "TOV": 0.0, "STL/TOV": null, "TSA": 6.88, "2PA": 6.0, "college": "", "FG": 2.0, "3PA": 0.0, "DRB": 5.0, "ORB%": 0.0, "BLK%": 0.0, "AST/TOV": null, "position": "C", "AST": 0.0, "FT%": 1.0, "3PAr": 0.0, "PF": 1.0, "PTS": 6.0, "FGA": 6.0, "DRBr": 1.0, "ORBr": 0.0, "2P": 2.0, "STL": 2.0, "TRB": 5.0, "TOV%": 0.0, "AST%": 0.0, "FTAr": 0.3333333333333333, "FTA": 2.0, "FIC": 6.0, "eFG%": 0.3333333333333333, "BLK": 0.0, "birth_date": "1986-01-03", "FG%": 0.3333333333333333, "2PAr": 1.0, "FTr": 0.333, "+/-": -9.0, "name": "Nikola Pekovic", "USG%": 20.4, "DRB%": 34.6, "TS%": 0.436046511627907, "experience": 4, "height": 1.8623506461838577, "2P%": 0.3333333333333333, "MP": 15.416666666666666, "DRtg": 91.0, "ORtg": 96.0, "TRB%": 16.6, "FT/FGA": 0.3333333333333333, "ORB": 0.0, "3P%": null, "HOB": 0.0625}, "Gorgui Dieng": {"STL%": 1.6, "": "sn", "FT": 4.0, "weight": "241", "3P": 0.0, "TOV": 3.0, "STL/TOV": 0.3333333333333333, "TSA": 6.76, "2PA": 5.0, "college": "University of Louisville", "FG": 2.0, "3PA": 0.0, "DRB": 6.0, "ORB%": 11.7, "BLK%": 4.0, "AST/TOV": 0.0, "position": "C", "AST": 0.0, "FT%": 1.0, "3PAr": 0.0, "PF": 4.0, "PTS": 8.0, "FGA": 5.0, "DRBr": 0.6, "ORBr": 0.4, "2P": 2.0, "STL": 1.0, "TRB": 10.0, "TOV%": 30.7, "AST%": 0.0, "FTAr": 0.8, "FTA": 4.0, "FIC": 9.25, "eFG%": 0.4, "BLK": 2.0, "birth_date": "1990-01-18", "FG%": 0.4, "2PAr": 1.0, "FTr": 0.8, "+/-": -15.0, "name": "Gorgui Dieng", "USG%": 13.4, "DRB%": 19.2, "TS%": 0.591715976331361, "experience": 1, "height": 1.8623506461838577, "2P%": 0.4, "MP": 33.36666666666667, "DRtg": 105.0, "ORtg": 97.0, "TRB%": 15.3, "FT/FGA": 0.8, "ORB": 4.0, "3P%": null, "HOB": 0.0625}, "Adreian Payne": {"STL%": 4.6, "": "us", "FT": 3.0, "weight": "237", "3P": 0.0, "TOV": 2.0, "STL/TOV": 1.0, "TSA": 5.76, "2PA": 4.0, "college": "Michigan State University", "FG": 1.0, "3PA": 0.0, "DRB": 4.0, "ORB%": 8.6, "BLK%": 2.9, "AST/TOV": 0.0, "position": "PF", "AST": 0.0, "FT%": 0.75, "3PAr": 0.0, "PF": 0.0, "PTS": 5.0, "FGA": 4.0, "DRBr": 0.6666666666666666, "ORBr": 0.3333333333333333, "2P": 1.0, "STL": 2.0, "TRB": 6.0, "TOV%": 25.8, "AST%": 0.0, "FTAr": 1.0, "FTA": 4.0, "FIC": 6.5, "eFG%": 0.25, "BLK": 1.0, "birth_date": "1991-02-19", "FG%": 0.25, "2PAr": 1.0, "FTr": 1.0, "+/-": -12.0, "name": "Adreian Payne", "USG%": 15.5, "DRB%": 18.7, "TS%": 0.4340277777777778, "experience": 0, "height": 1.8593026091197267, "2P%": 0.25, "MP": 22.833333333333332, "DRtg": 100.0, "ORtg": 79.0, "TRB%": 13.4, "FT/FGA": 0.75, "ORB": 2.0, "3P%": null, "HOB": 0.03125}, "Kevin Garnett": {"STL%": 0.0, "": "us", "FT": 1.0, "weight": "240", "3P": 0.0, "TOV": 0.0, "STL/TOV": null, "TSA": 6.88, "2PA": 6.0, "college": "", "FG": 5.0, "3PA": 0.0, "DRB": 6.0, "ORB%": 0.0, "BLK%": 3.2, "AST/TOV": null, "position": "PF", "AST": 2.0, "FT%": 0.5, "3PAr": 0.0, "PF": 3.0, "PTS": 11.0, "FGA": 6.0, "DRBr": 1.0, "ORBr": 0.0, "2P": 5.0, "STL": 0.0, "TRB": 6.0, "TOV%": 0.0, "AST%": 22.0, "FTAr": 0.3333333333333333, "FTA": 2.0, "FIC": 11.75, "eFG%": 0.8333333333333334, "BLK": 1.0, "birth_date": "1976-05-19", "FG%": 0.8333333333333334, "2PAr": 1.0, "FTr": 0.333, "+/-": 5.0, "name": "Kevin Garnett", "USG%": 14.9, "DRB%": 30.3, "TS%": 0.7994186046511628, "experience": 19, "height": 1.8623506461838577, "2P%": 0.8333333333333334, "MP": 21.15, "DRtg": 105.0, "ORtg": 162.0, "TRB%": 14.5, "FT/FGA": 0.16666666666666666, "ORB": 0.0, "3P%": null, "HOB": 0.21875}, "Glenn Robinson": {"": "us", "name": "Glenn Robinson", "weight": "222", "experience": 0, "height": 2.0117044623262617, "college": "University of Michigan", "MP": 0.0, "birth_date": "1994-01-08", "position": "SG"}, "Gary Neal": {"STL%": 1.8, "": "us", "FT": 0.0, "weight": "210", "3P": 1.0, "TOV": 0.0, "STL/TOV": null, "TSA": 13.0, "2PA": 9.0, "college": "Towson University", "FG": 6.0, "3PA": 4.0, "DRB": 3.0, "ORB%": 0.0, "BLK%": 0.0, "AST/TOV": null, "position": "SG", "AST": 2.0, "FT%": null, "3PAr": 0.3076923076923077, "PF": 2.0, "PTS": 13.0, "FGA": 13.0, "DRBr": 1.0, "ORBr": 0.0, "2P": 5.0, "STL": 1.0, "TRB": 3.0, "TOV%": 0.0, "AST%": 15.4, "FTAr": 0.0, "FTA": 0.0, "FIC": 7.5, "eFG%": 0.5, "BLK": 0.0, "birth_date": "1984-10-03", "FG%": 0.46153846153846156, "2PAr": 0.6923076923076923, "FTr": 0.0, "+/-": -19.0, "name": "Gary Neal", "USG%": 20.8, "DRB%": 11.2, "TS%": 0.5, "experience": 4, "height": 1.9507437210436478, "2P%": 0.5555555555555556, "MP": 28.533333333333335, "DRtg": 111.0, "ORtg": 107.0, "TRB%": 5.4, "FT/FGA": 0.0, "ORB": 0.0, "3P%": 0.25, "HOB": 0.25}, "Ricky Rubio": {"STL%": 1.3, "": "es", "FT": 2.0, "weight": "194", "3P": 0.0, "TOV": 4.0, "STL/TOV": 0.25, "TSA": 13.88, "2PA": 10.0, "college": "", "FG": 4.0, "3PA": 3.0, "DRB": 1.0, "ORB%": 4.8, "BLK%": 0.0, "AST/TOV": 2.5, "position": "PG", "AST": 10.0, "FT%": 1.0, "3PAr": 0.23076923076923078, "PF": 0.0, "PTS": 10.0, "FGA": 13.0, "DRBr": 0.3333333333333333, "ORBr": 0.6666666666666666, "2P": 4.0, "STL": 1.0, "TRB": 3.0, "TOV%": 22.4, "AST%": 43.3, "FTAr": 0.15384615384615385, "FTA": 2.0, "FIC": 9.25, "eFG%": 0.3076923076923077, "BLK": 0.0, "birth_date": "1990-10-21", "FG%": 0.3076923076923077, "2PAr": 0.7692307692307693, "FTr": 0.154, "+/-": -4.0, "name": "Ricky Rubio", "USG%": 20.1, "DRB%": 2.6, "TS%": 0.36023054755043227, "experience": 3, "height": 1.9507437210436478, "2P%": 0.4, "MP": 40.63333333333333, "DRtg": 115.0, "ORtg": 81.0, "TRB%": 3.8, "FT/FGA": 0.15384615384615385, "ORB": 2.0, "3P%": 0.0, "HOB": 0.4375}, "Kevin Martin": {"STL%": 0.0, "": "us", "FT": 2.0, "weight": "199", "3P": 1.0, "TOV": 1.0, "STL/TOV": 0.0, "TSA": 16.32, "2PA": 9.0, "college": "Western Carolina University", "FG": 3.0, "3PA": 6.0, "DRB": 2.0, "ORB%": 3.3, "BLK%": 0.0, "AST/TOV": 2.0, "position": "SG", "AST": 2.0, "FT%": 0.6666666666666666, "3PAr": 0.4, "PF": 1.0, "PTS": 9.0, "FGA": 15.0, "DRBr": 0.6666666666666666, "ORBr": 0.3333333333333333, "2P": 2.0, "STL": 0.0, "TRB": 3.0, "TOV%": 5.8, "AST%": 11.7, "FTAr": 0.2, "FTA": 3.0, "FIC": -0.375, "eFG%": 0.23333333333333334, "BLK": 0.0, "birth_date": "1983-02-01", "FG%": 0.2, "2PAr": 0.6, "FTr": 0.2, "+/-": -6.0, "name": "Kevin Martin", "USG%": 26.3, "DRB%": 7.1, "TS%": 0.2757352941176471, "experience": 10, "height": 2.042184832967569, "2P%": 0.2222222222222222, "MP": 30.066666666666666, "DRtg": 116.0, "ORtg": 65.0, "TRB%": 5.1, "FT/FGA": 0.13333333333333333, "ORB": 1.0, "3P%": 0.16666666666666666, "HOB": 0.15625}, "Chase Budinger": {"": "us", "name": "Chase Budinger", "weight": "209", "experience": 5, "height": 2.042184832967569, "college": "University of Arizona", "MP": 0.0, "birth_date": "1988-05-22", "position": "SF"}, "Andrew Wiggins": {"STL%": 0.0, "": "ca", "FT": 4.0, "weight": "199", "3P": 0.0, "TOV": 0.0, "STL/TOV": null, "TSA": 19.52, "2PA": 14.0, "college": "University of Kansas", "FG": 8.0, "3PA": 2.0, "DRB": 3.0, "ORB%": 5.1, "BLK%": 1.8, "AST/TOV": null, "position": "SF", "AST": 1.0, "FT%": 0.5, "3PAr": 0.125, "PF": 3.0, "PTS": 20.0, "FGA": 16.0, "DRBr": 0.6, "ORBr": 0.4, "2P": 8.0, "STL": 0.0, "TRB": 5.0, "TOV%": 0.0, "AST%": 5.8, "FTAr": 0.5, "FTA": 8.0, "FIC": 9.75, "eFG%": 0.5, "BLK": 1.0, "birth_date": "1995-02-23", "FG%": 0.5, "2PAr": 0.875, "FTr": 0.5, "+/-": -7.0, "name": "Andrew Wiggins", "USG%": 23.5, "DRB%": 8.4, "TS%": 0.5122950819672131, "experience": 0, "height": 2.0726652036088757, "2P%": 0.5714285714285714, "MP": 38.05, "DRtg": 114.0, "ORtg": 111.0, "TRB%": 6.7, "FT/FGA": 0.25, "ORB": 2.0, "3P%": 0.0, "HOB": 0.28125}}, "scores": {"1": "27", "3": "22", "2": "16", "4": "20", "T": "85"}, "name": "Minnesota Timberwolves", "totals": {"STL%": 7.6, "FT": 18.0, "2PA": 64.0, "FG": 32.0, "DRB": 31.0, "ORB%": 24.5, "AST": 18.0, "3PAr": 0.21951219512195122, "PF": 16.0, "FGA": 82.0, "DRBr": 0.7209302325581395, "2P": 29.0, "ORBr": 0.27906976744186046, "TOV%": 11.4, "AST%": 56.3, "FTAr": 0.3048780487804878, "FIC": 59.375, "eFG%": 0.40853658536585363, "FG%": 0.3902439024390244, "2PAr": 0.7804878048780488, "+/-": -15.0, "USG%": 100.0, "DRtg": 109.1, "2P%": 0.453125, "DRB%": 68.9, "ORtg": 92.8, "TRB%": 45.7, "ORB": 12.0, "3P": 3.0, "TOV": 12.0, "STL/TOV": 0.5833333333333334, "TSA": 93.0, "AST/TOV": 1.5, "3PA": 18.0, "BLK%": 6.9, "FT%": 0.72, "PTS": 85.0, "HOB": 1.5625, "STL": 7.0, "TRB": 43.0, "FTA": 25.0, "BLK": 5.0, "FTr": 0.305, "TS%": 0.45698924731182794, "FT/FGA": 0.21951219512195122, "3P%": 0.16666666666666666}}, "type": "Season"}